Workbook
Name AWS_Shared_Pct: Assumptions!$B$12
Name Departments_Table: 'Data Dictionary'!$A$14:$C$20
Name InsureSight_Split: Assumptions!$B$6
Name Products_Table: 'Data Dictionary'!$A$6:$D$9
Name Revenue_Share_Pct_iGO: Assumptions!$B$8
Name Vendors_Table: 'Data Dictionary'!$A$40:$D$54

Sheet CrossfireHiddenWorksheet
A1: ID | B1: Date | C1: Department | D1: Product | E1: Expense Category | F1: Vendor | G1: Amount
A2: c15c63af-93b1-46c7-8644-3820dad92ebe | B2: 7/13/2025 | C2: R&D | D2: DocFast | E2: Connectivity Charges | F2: Salesforce Inc. | G2: 14607.17
A3: 8a85fdcf-6ebb-4953-b8da-7162bdf9a3d5 | B3: 08/23/2025 | C3: Partners | D3: InsureSight | E3: Overhead Allocation & Chargebacks | F3: Palo Alto Networks | G3: 12027.16
A4: c8a310f7-0591-4f07-993b-442ed4044da5 | B4: 2025-12-14 | C4: NetOps | D4: DocFast | E4: Other | F4: Microsoft Corp. | G4: 2747.82
A5: 69e58234-9c0b-4205-8df2-6c9fb98fb403 | B5: 45788 | C5: NetOps | D5: iGO | E5: AWS | F5: Deloitte Consulting | G5: 4469.82
A6: 4722607f-0537-44bf-9194-320a67cfcac4 | B6: 45889 | C6: R&D | D6: DocFast | E6: Advertising and Promotion Expense | F6: Iron Mountain | G6: 6686.43
A7: ce278d40-1e9d-4d2e-9373-fa1300bc4c3a | B7: 45871 | C7: R&D | D7: InsureSight | E7: Other | F7: Zendesk Inc. | G7: 4154.6
A8: 967517e0-f2d6-4f2a-84dc-911fa2893d68 | B8: 45660 | C8: R&D | D8: DocFast | E8: AWS | F8: Cognizant Technology | G8: 12026.38
A9: 2bd05c39-f827-4f27-9e3e-fc6ad796018b | B9: 45967 | C9: NetOps | D9: Affirm | E9: Other | F9: Deloitte Consulting | G9: 11730.61
A10: cde97481-ee1b-4ab4-9d65-3621e2ce790a | B10: 45662 | C10: NetOps | D10: Affirm | E10: Reselling Expenses | F10: Salesforce Inc. | G10: 5464.15
A11: c83d288d-09e6-43dd-b598-4fbc1ab163e7 | B11: 45932 | C11: Content | D11: Affirm | E11: Reselling Expenses | F11: Accenture LLP | G11: 14234.91
A12: c7c3d879-f4ea-42fe-8689-04637efe504b | B12: 45823 | C12: Product Management | D12: iGO | E12: Other | F12: Datadog Inc. | G12: 7965.43
A13: e36d0d88-4984-4c14-a188-4d0fbb5660b6 | B13: 45849 | C13: R&D | D13: InsureSight | E13: Software and Maintenance Expense | F13: Cloudflare Inc. | G13: 437.4
A14: 53eb0a32-96ae-4a39-9676-5bb87485f3fb | B14: 45732 | C14: Content | D14: DocFast | E14: Overhead Allocation & Chargebacks | F14: Cloudflare Inc. | G14: 3963.56
A15: b694b8c0-ad82-4b3c-b286-f4646bd17732 | B15: 45800 | C15: Partners | D15: Affirm | E15: Other | F15: Palo Alto Networks | G15: 10425.01
A16: 7af83a40-5271-4700-a4c8-f992eb7cd1bd | B16: 45876 | C16: NetOps | D16: Affirm | E16: Professional Fees and Outsourcing Expenses | F16: Accenture LLP | G16: 2631.21
... A64: 4596d386-69da-454d-9d57-1a3ecc03ac5b | B64: 46000 | C64: Support | D64: iGO | E64: Other | F64: Deloitte Consulting | G64: 8170.7
A65: ddedef0a-7dd1-4249-835b-5e50f49ff792 | B65: 45865 | C65: Support | D65: Affirm | E65: Data Center Fees | F65: Amazon Web Services | G65: 4350.07
A66: 203c77e4-22ab-4ba5-8e21-17a361c28a6c | B66: 45994 | C66: Support | D66: DocFast | E66: Reselling Expenses | F66: Palo Alto Networks | G66: 11222.71
A67: 51e8f173-f795-49b0-8e52-d6cfa8bbc774 | B67: 45754 | C67: Product Management | D67: InsureSight | E67: Overhead Allocation & Chargebacks | F67: Iron Mountain | G67: 4110.74
A68: f055e65a-d4ee-424a-8e6a-ccf0a966085e | B68: 45708 | C68: R&D | D68: Affirm | E68: Software and Maintenance Expense | F68: Amazon Web Services | G68: 10064.02
A69: 06ea6433-87ae-43db-8206-bcbb22cf9a89 | B69: 45908 | C69: R&D | D69: Affirm | E69: Employee Expenses | F69: Cloudflare Inc. | G69: 6228.86
A70: 5975f85b-0ab3-4fa7-b809-862b6c1c2b22 | B70: 46007 | C70: NetOps | D70: Affirm | E70: Employee Expenses | F70: Cognizant Technology | G70: 14669.77
A71: ad812bfa-99b4-45eb-91bf-e78f1dbf9b21 | B71: 45730 | C71: R&D | D71: DocFast | E71: Office Expenses & Rent Allocation | F71: Deloitte Consulting | G71: 3031.87
A72: 5e55d144-0002-4cbe-b42b-5e24286b2fe4 | B72: 45788 | C72: Support | D72: iGO | E72: Professional Fees and Outsourcing Expenses | F72: Deloitte Consulting | G72: 8633.29
A73: 8ecfeee2-4b6b-4b55-8c5e-902f8e83b0c2 | B73: 45924 | C73: R&D | D73: iGO | E73: Advertising and Promotion Expense | F73: Zendesk Inc. | G73: 13239.56
A74: 8b5b8e4d-82e2-4f4b-b46a-a7832229ec93 | B74: 45718 | C74: Product Management | D74: DocFast | E74: Office Expenses & Rent Allocation | F74: Datadog Inc. | G74: 14052.3
A75: dd2d405d-95fa-48cf-b462-f98775d460ec | B75: 45779 | C75: NetOps | D75: InsureSight | E75: Other | F75: WillisTowersWatson | G75: 1654.15
A76: 170d59d3-aea9-44d6-b3ea-bb3fb3e83e55 | B76: 45818 | C76: Partners | D76: DocFast | E76: Advertising and Promotion Expense | F76: Microsoft Corp. | G76: 7587.98
A77: 384c5824-52a4-49c6-bfbe-7887cbfc33e7 | B77: 45784 | C77: Product Management | D77: iGO | E77: AWS | F77: Datadog Inc. | G77: 10980.23
... A140: f7b7696f-78c1-4ed9-822e-3a6ca0d7bbd0 | B140: 45710 | C140: Support | D140: iGO | E140: Advertising and Promotion Expense | F140: Atlassian Inc. | G140: 12763.89
A141: 5dff82f5-122c-474b-b28d-dfb0916fc44e | B141: 45664 | C141: Content | D141: Affirm | E141: Connectivity Charges | F141: Atlassian Inc. | G141: 1200.22
A142: 0681f2d0-e922-44b1-84fb-25a72ad5a95f | B142: 45735 | C142: Security | D142: DocFast | E142: Reselling Expenses | F142: Atlassian Inc. | G142: 8131.41
A143: 978542e6-fdb4-42b9-9198-446cf0b56b06 | B143: 45863 | C143: R&D | D143: Affirm | E143: Professional Fees and Outsourcing Expenses | F143: Cognizant Technology | G143: 11194.58
A144: 23a4c0d1-e0cd-4769-bc09-08ea55184622 | B144: 45810 | C144: NetOps | D144: DocFast | E144: Software and Maintenance Expense | F144: Microsoft Corp. | G144: 1186.47
A145: bb616d7e-3da6-4c64-adc5-24f38fb8dabf | B145: 45955 | C145: Content | D145: DocFast | E145: AWS | F145: Amazon Web Services | G145: 9530.14
A146: f59ee2e0-f6dc-4964-8a8b-7581d5c7eef9 | B146: 45885 | C146: Security | D146: InsureSight | E146: Overhead Allocation & Chargebacks | F146: Zendesk Inc. | G146: 6506.13
A147: 9fdd55d6-212c-42ba-9e8a-c671bfe322a1 | B147: 45980 | C147: R&D | D147: DocFast | E147: Professional Fees and Outsourcing Expenses | F147: Adobe Systems | G147: 9298.31
A148: 72866fa6-69d2-4950-a9d8-35f076cb197c | B148: 45770 | C148: NetOps | D148: iGO | E148: Data Center Fees | F148: Datadog Inc. | G148: 5731
A149: bb6e0962-387a-4751-b9b5-5065412c5f26 | B149: 45966 | C149: R&D | D149: DocFast | E149: AWS | F149: Salesforce Inc. | G149: 1642.94
A150: 40e3680e-586d-4a1f-94ab-07f1e73d73e8 | B150: 45667 | C150: Partners | D150: InsureSight | E150: Data Center Fees | F150: Cloudflare Inc. | G150: 2030.98
A151: c957b30c-a824-4046-911a-ad6242206c99 | B151: 45730 | C151: Partners | D151: DocFast | E151: Professional Fees and Outsourcing Expenses | F151: Amazon Web Services | G151: 1389.8
A152: 4ed92bb4-638e-4bcf-b9ab-3d5fa7a9467d | B152: 45903 | C152: Content | D152: InsureSight | E152: Connectivity Charges | F152: Amazon Web Services | G152: 4413.12
A153: 2d3c0bfe-7c8a-44b9-b303-d7c8c3d3afb0 | B153: 45863 | C153: NetOps | D153: Affirm | E153: Other | F153: Cognizant Technology | G153: 2585.26
... A170: 3c8d5e7d-54c3-4e3f-bcde-6ea49ba03c50 | B170: 45863 | C170: Support | D170: DocFast | E170: Professional Fees and Outsourcing Expenses | F170: Amazon Web Services | G170: 1524.17
A171: 355798f3-6cd6-4a66-af29-6b94edcf3390 | B171: 45764 | C171: R&D | D171: Affirm | E171: Office Expenses & Rent Allocation | F171: Salesforce Inc. | G171: 5897.46
A172: 579afa9d-0e02-4034-9add-569dbb431443 | B172: 45980 | C172: R&D | D172: Affirm | E172: AWS | F172: Amazon Web Services | G172: 7267.43
A173: 651ec152-b163-4320-9229-803f9318c9df | B173: 45791 | C173: NetOps | D173: iGO | E173: Advertising and Promotion Expense | F173: Salesforce Inc. | G173: 4712.76
A174: 10dd86b7-c798-4202-a87f-0ac91c18f5f9 | B174: 45895 | C174: Security | D174: DocFast | E174: AWS | F174: Accenture LLP | G174: 1509.46
A175: bccff6a0-9cca-4fcf-af1b-be3eb6bb94aa | B175: 46014 | C175: Partners | D175: InsureSight | E175: Professional Fees and Outsourcing Expenses | F175: Palo Alto Networks | G175: 718.01
A176: 40162953-6c84-421a-a9ab-1d0136df5f90 | B176: 45995 | C176: NetOps | D176: InsureSight | E176: Reselling Expenses | F176: Cloudflare Inc. | G176: 10173.23
A177: affc2f03-b0e1-478e-a768-b5e3fb81d390 | B177: 45740 | C177: Security | D177: Affirm | E177: Overhead Allocation & Chargebacks | F177: Datadog Inc. | G177: 4998.3
A178: 2ec4ead6-bbc2-41bc-be5b-55da0fe6a889 | B178: 45853 | C178: Security | D178: DocFast | E178: Reselling Expenses | F178: Datadog Inc. | G178: 2836.48
A179: b7b60a43-b943-4357-aaff-e4301cb5b563 | B179: 45975 | C179: Partners | D179: iGO | E179: Other | F179: Atlassian Inc. | G179: 3000
A180: 8c10b78e-bc1d-4425-a975-c6d9d6baa48d | B180: 45944 | C180: Partners | D180: iGO | E180: Software and Maintenance Expense | F180: CrowdStrike Holdings | G180: 4211.26
A181: 4f789472-0570-49b2-8711-207eb865e6ea | B181: 46017 | C181: Product Management | D181: iGO | E181: Other | F181: Cloudflare Inc. | G181: 12002.56
A182: f705db10-0b39-40b4-b0a5-a703c4b11b39 | B182: 45906 | C182: Support | D182: InsureSight | E182: Software and Maintenance Expense | F182: Accenture LLP | G182: 1753.63
A183: 128e819c-53f2-4465-81c5-521e21e99e9f | B183: 45989 | C183: Partners | D183: InsureSight | E183: Other | F183: Zendesk Inc. | G183: 9189.06
... A189: 0a66c308-e330-46cc-952b-c484376a284d | B189: 45967 | C189: Content | D189: Affirm | E189: Office Expenses & Rent Allocation | F189: Palo Alto Networks | G189: 2147.43
A190: 519b461b-3d97-4769-a2ed-2ad33c2483c8 | B190: 45835 | C190: Partners | D190: iGO | E190: AWS | F190: Amazon Web Services | G190: 7294.9
A191: 64b579d8-0e86-4bd8-af2d-8dd425dd8ea7 | B191: 45774 | C191: Partners | D191: DocFast | E191: Connectivity Charges | F191: Deloitte Consulting | G191: 7401.3
A192: 72c91da2-1a4b-407f-98e5-36d8a810aed3 | B192: 46018 | C192: Partners | D192: DocFast | E192: Advertising and Promotion Expense | F192: Cloudflare Inc. | G192: 8502.7
A193: 9a73e01c-5f1b-4e87-8acb-cd6c1de9abb9 | B193: 45757 | C193: NetOps | D193: InsureSight | E193: Software and Maintenance Expense | F193: Cognizant Technology | G193: 4365.62
A194: d326af71-2457-4b1b-b8c5-1a73650e09de | B194: 45888 | C194: R&D | D194: DocFast | E194: Overhead Allocation & Chargebacks | F194: Cognizant Technology | G194: 1742.5
A195: a892459e-a1e2-41a8-b676-0c809f441731 | B195: 45697 | C195: Product Management | D195: InsureSight | E195: Overhead Allocation & Chargebacks | F195: Microsoft Corp. | G195: 11363.95
A196: e5fefd70-c093-4ae8-8a14-212c18d00500 | B196: 46006 | C196: Content | D196: Affirm | E196: Connectivity Charges | F196: Cloudflare Inc. | G196: 11053.03
A197: 9b1cf0a9-30c1-42d7-b35d-51be1e314a10 | B197: 45986 | C197: Security | D197: InsureSight | E197: Employee Expenses | F197: Accenture LLP | G197: 3979.09
A198: 26fb2d81-f175-4445-b120-ad88c63931a7 | B198: 45703 | C198: Product Management | D198: iGO | E198: Software and Maintenance Expense | F198: CrowdStrike Holdings | G198: 12170.01
A199: 447f5d6f-48ce-4357-a4a8-e664de482db0 | B199: 45953 | C199: Support | D199: DocFast | E199: Advertising and Promotion Expense | F199: WillisTowersWatson | G199: 2131.56
A200: 310cc424-859d-4f55-a4c4-7f48e2ca28ce | B200: 45774 | C200: Security | D200: iGO | E200: Other | F200: Salesforce Inc. | G200: 8007.6
A201: 898fbca3-4086-476e-b2eb-e33082cb088c | B201: 45948 | C201: Security | D201: InsureSight | E201: Data Center Fees | F201: Palo Alto Networks | G201: 8612.4
A202: 9041af7f-48de-4098-965b-4d9662e20ddf | B202: 45922 | C202: Product Management | D202: iGO | E202: Advertising and Promotion Expense | F202: Adobe Systems | G202: 11796.08
... A410: d6f6e5c5-dab8-4088-b99f-4bc2ac99767d | B410: 45905 | C410: Partners | D410: iGO | E410: Overhead Allocation & Chargebacks | F410: Iron Mountain | G410: 776.15
A411: 630c62d6-ce07-4ddd-b553-4c8ea3dec878 | B411: 45865 | C411: Content | D411: DocFast | E411: Overhead Allocation & Chargebacks | F411: Adobe Systems | G411: 13821.38
A412: 7a9d0175-d3a3-4217-81f6-a423918622de | B412: 45739 | C412: Content | D412: Affirm | E412: Advertising and Promotion Expense | F412: Cloudflare Inc. | G412: 5841.71
A413: 2a01f921-645b-4605-a378-88f1598bf194 | B413: 45950 | C413: Support | D413: DocFast | E413: Connectivity Charges | F413: WillisTowersWatson | G413: 13742.86
A414: 42bf0807-b748-4ec4-8ada-e625a81d27e9 | B414: 45756 | C414: Partners | D414: InsureSight | E414: Data Center Fees | F414: Accenture LLP | G414: 12081.71
A415: 43acad3a-a430-4e4e-98c4-0001a69f83c7 | B415: 45730 | C415: Content | D415: InsureSight | E415: Overhead Allocation & Chargebacks | F415: Microsoft Corp. | G415: 4742.97
A416: 80ef8a0b-6303-44a4-bd4d-7bc54a33d0a6 | B416: 46009 | C416: R&D | D416: Affirm | E416: Software and Maintenance Expense | F416: CrowdStrike Holdings | G416: 9381.31
A417: d7929933-4c1e-4ca9-9d15-0e5ffe32a04d | B417: 45799 | C417: Support | D417: Affirm | E417: Reselling Expenses | F417: Datadog Inc. | G417: 7583.21
A418: 499ae31a-591a-4025-b6c6-3ecefa95d889 | B418: 46012 | C418: Support | D418: iGO | E418: AWS | F418: Cognizant Technology | G418: 7231.53
A419: 45547bae-2a39-44a6-aff4-1b62e2066854 | B419: 45952 | C419: R&D | D419: DocFast | E419: Reselling Expenses | F419: Iron Mountain | G419: 13413.3
A420: 3cf881d1-f26c-4210-89dc-944500a7e1d5 | B420: 45910 | C420: Product Management | D420: DocFast | E420: Employee Expenses | F420: Cognizant Technology | G420: 1641.73
A421: 0fdeb4a2-82c3-450f-84ab-527d71f7af78 | B421: 45843 | C421: NetOps | D421: iGO | E421: Software and Maintenance Expense | F421: Palo Alto Networks | G421: 11265.27
A422: 444219d7-f6b1-4e87-bb7f-eeee6ce87a73 | B422: 45726 | C422: R&D | D422: InsureSight | E422: Advertising and Promotion Expense | F422: Microsoft Corp. | G422: 977.39
A423: af027ff1-17ef-418e-a0b6-caac8f4c6ae6 | B423: 45784 | C423: Product Management | D423: iGO | E423: AWS | F423: Microsoft Corp. | G423: 6816.29
... A511: f2af505f-d405-4549-9e3d-15c007adc640 | B511: 45729 | C511: Support | D511: InsureSight | E511: Advertising and Promotion Expense | F511: Datadog Inc. | G511: 10946.02

Sheet Assumptions
A1: Keystone BenefitTech, Inc. | D1: Last Updated: 2026-02-28
A2: Assumptions & Driver Table
A4: DRIVER TABLE
A5: Driver Name | B5: Value | C5: Type | D5: Notes
A6: InsureSight Software Split - InsureSight | B6: 0.22 | C6: Percentage | D6: 22% stays on InsureSight (INTENTIONALLY stored as text for demo)
A7: InsureSight Software Split - Other | B7: 0.78 | C7: Percentage | D7: 78% allocated to iGO, DocFast, Content
A8: iGO Revenue Share % | B8: 0.55 | C8: Percentage | D8: iGO share of total subscription + transaction revenue
A9: Affirm Revenue Share % | B9: 0.28 | C9: Percentage | D9: Affirm share of total subscription + transaction revenue
A10: InsureSight Revenue Share % | B10: 0.12 | C10: Percentage | D10: InsureSight share
A11: DocFast Revenue Share % | B11: 0.05 | C11: Percentage | D11: DocFast share
A12: AWS Shared Pool % | B12: 0.3 | C12: Percentage | D12: Percentage of AWS costs in shared pool
A13: AWS Direct % | B13: 0.7 | C13: Percentage | D13: Percentage of AWS costs directly allocated
A14: Monthly Growth Rate Target | B14: 0.02 | C14: Percentage | D14: Target 2% monthly revenue growth
A15: Q4 Seasonality Uplift | B15: 0.05 | C15: Percentage | D15: 5% Q4 revenue uplift
A16: D&A Rate | B16: 0.01 | C16: Percentage | D16: Depreciation & amortization as % of revenue
A17: R&D Capitalization Rate | B17: 0.3 | C17: Percentage | D17: 30% of R&D capitalized
A18: Employee Cost Allocation Base | B18: 1 | C18: Multiplier | D18: 1.0x base for employee cost allocation
A19: Standard Overhead Rate | B19: 500 | C19: Dollar | D19: Monthly overhead allocation per department
A23: ALLOCATION METHODOLOGY
A24: Department | B24: Allocation Methodology
A25: Revenue | B25: Revenue has been scrubbed and reclassified. Monthly journal entries in Intacct ensure revenue is properly allocated to product lines based on contractual terms and billing records.
A26: NetOps | B26: AWS costs are allocated by product line based on the AWS Allocation Tab. Shared AWS costs are distributed by compute share %. Non-AWS costs (employee, vendor) are allocated pro-rata based on subscription + transaction revenue share by product.
A27: Security | B27: All costs allocated based on percentage of subscription + transaction revenue by product line. No direct employee assignment — treated as shared infrastructure cost.
A28: Support | B28: Employee costs allocated by product lines assigned per management direction. Vendor costs tied to specific products. Remainder allocated pro-rata based on employee headcount by product.
A29: Partners | B29: Vendor costs tied to specific products. InsureSight software costs split 22% to InsureSight and 78% allocated to iGO, DocFast, and Content based on user mix driver. Employee costs by assignment.
A30: Content | B30: Employee costs allocated by product assignment. Vendor costs tied to specific products. Remainder allocated pro-rata based on employee headcount.
A31: Pro Services | B31: Same pattern: employee assignment + vendor-tied + prorata remainder based on employee headcount allocation.
A32: R&D | B32: Same pattern: employee assignment + vendor-tied + prorata remainder based on employee headcount allocation. Includes capitalized software development costs.
A33: Product Management | B33: Same pattern: employee assignment + vendor-tied + prorata remainder based on employee headcount allocation.

Sheet Data Dictionary
A1: Keystone BenefitTech, Inc. | E1: Last Updated: 2026-02-28
A2: Data Dictionary
A4: PRODUCTS
A5: Product Code | B5: Product Name | C5: Product Category | D5: Status
A6: PROD-001 | B6: iGO | C6: Subscription | D6: Active
A7: PROD-002 | B7: Affirm | C7: Subscription | D7: Active
A8: PROD-003 | B8: InsureSight | C8: Mixed | D8: Active
A9: PROD-004 | B9: DocFast | C9: Services | D9: Active
A12: DEPARTMENTS
A13: Department Code | B13: Department Name | C13: Cost Type
A14: DEPT-001 | B14: NetOps | C14: Direct
A15: DEPT-002 | B15: Security | C15: Indirect
A16: DEPT-003 | B16: Support | C16: Direct
A17: DEPT-004 | B17: Partners | C17: Direct
A18: DEPT-005 | B18: Content | C18: Direct
A19: DEPT-006 | B19: R&D | C19: Indirect
A20: DEPT-007 | B20: Product Management | C20: Overhead
A23: EXPENSE CATEGORIES
A24: Category Code | B24: Category Name | C24: GL Account Range | D24: Typical Department
A25: EXP-001 | B25: Employee Expenses | C25: 5000-5199 | D25: All
A26: EXP-002 | B26: Professional Fees and Outsourcing Expenses | C26: 5200-5299 | D26: All
A27: EXP-003 | B27: Advertising and Promotion Expense | C27: 5300-5399 | D27: R&D
A28: EXP-004 | B28: Software and Maintenance Expense | C28: 5400-5499 | D28: All
A29: EXP-005 | B29: Data Center Fees | C29: 5500-5549 | D29: NetOps
A30: EXP-006 | B30: AWS | C30: 5550-5599 | D30: NetOps
A31: EXP-007 | B31: Connectivity Charges | C31: 5600-5649 | D31: NetOps
A32: EXP-008 | B32: Office Expenses & Rent Allocation | C32: 5700-5799 | D32: All
A33: EXP-009 | B33: Overhead Allocation & Chargebacks | C33: 5800-5899 | D33: All
A34: EXP-010 | B34: Other | C34: 5900-5999 | D34: All
A35: EXP-011 | B35: Reselling Expenses | C35: 6000-6099 | D35: Partners
A38: VENDORS
A39: Vendor Code | B39: Vendor Name | C39: Primary Department | D39: Primary Product
A40: VEND-001 | B40: Amazon Web Services | C40: NetOps | D40: All
A41: VEND-002 | B41: Cloudflare Inc. | C41: NetOps | D41: All
A42: VEND-003 | B42: Datadog Inc. | C42: NetOps | D42: All
A43: VEND-004 | B43: CrowdStrike Holdings | C43: Security | D43: All
A44: VEND-005 | B44: Palo Alto Networks | C44: Security | D44: All
A45: VEND-006 | B45: Salesforce Inc. | C45: Support | D45: iGO
A46: VEND-007 | B46: Zendesk Inc. | C46: Support | D46: Affirm
A47: VEND-008 | B47: Accenture LLP | C47: R&D | D47: All
A48: VEND-009 | B48: Cognizant Technology | C48: R&D | D48: InsureSight
A49: VEND-010 | B49: WillisTowersWatson | C49: Partners | D49: InsureSight
A50: VEND-011 | B50: Deloitte Consulting | C50: Partners | D50: All
... A54: VEND-015 | B54: Atlassian Inc. | C54: Product Management | D54: All

Sheet AWS Allocation
A1: Keystone BenefitTech, Inc. | F1: Last Updated: 2026-02-28
A2: AWS Cost Allocation Model
A4: SECTION 1: Product Compute Shares
A5: Product | B5: Compute Share % | C5: Monthly AWS Pool ($)
A6: iGO | B6: 0.45 | C6: See Section 2
A7: Affirm | B7: 0.25 | C7: See Section 2
A8: InsureSight | B8: 0.2 | C8: See Section 2
A9: DocFast | B9: 0.1 | C9: See Section 2
A10: Total | B10: =SUM(B6:B9)
A13: SECTION 2: Monthly AWS Cost Pool
A14: Month | B14: Total AWS Cost Pool ($) | C14: Shared AWS % | D14: Direct AWS %
A15: Jan 2025 | B15: 1907.66 | C15: 0.3 | D15: 0.7
A16: Feb 2025 | B16: 1808.49 | C16: 0.3 | D16: 0.7
A17: Mar 2025 | B17: 2120.48 | C17: 0.3 | D17: 0.7
A18: Apr 2025 | B18: 1964.59 | C18: 0.3 | D18: 0.7
A19: May 2025 | B19: 2384.58 | C19: 0.3 | D19: 0.7
A20: Jun 2025 | B20: 2132.02 | C20: 0.3 | D20: 0.7
A21: Jul 2025 | B21: 2218.45 | C21: 0.3 | D21: 0.7
A22: Aug 2025 | B22: 1875.77 | C22: 0.3 | D22: 0.7
A23: Sep 2025 | B23: 2321.08 | C23: 0.3 | D23: 0.7
A24: Oct 2025 | B24: 2094.53 | C24: 0.3 | D24: 0.7
A25: Nov 2025 | B25: 2323.63 | C25: 0.3 | D25: 0.7
A26: Dec 2025 | B26: 2144.44 | C26: 0.3 | D26: 0.7
A29: SECTION 3: Allocated AWS by Product by Month
A30: Month | B30: iGO | C30: Affirm | D30: InsureSight | E30: DocFast | F30: Total
A31: Jan 2025 | B31: =$B$6*$B$15 | C31: =$B$7*$B$15 | D31: =$B$8*$B$15 | E31: =$B$9*$B$15 | F31: =SUM(B31:E31)
A32: Feb 2025 | B32: =$B$6*$B$16 | C32: =$B$7*$B$16 | D32: =$B$8*$B$16 | E32: =$B$9*$B$16 | F32: =SUM(B32:E32)
A33: Mar 2025 | B33: =$B$6*$B$17 | C33: =$B$7*$B$17 | D33: =$B$8*$B$17 | E33: =$B$9*$B$17 | F33: =SUM(B33:E33)
A34: Apr 2025 | B34: =$B$6*$B$18 | C34: =$B$7*$B$18 | D34: =$B$8*$B$18 | E34: =$B$9*$B$18 | F34: =SUM(B34:E34)
A35: May 2025 | B35: =$B$6*$B$19 | C35: =$B$7*$B$19 | D35: =$B$8*$B$19 | E35: =$B$9*$B$19 | F35: =SUM(B35:E35)
A36: Jun 2025 | B36: =$B$6*$B$20 | C36: =$B$7*$B$20 | D36: =$B$8*$B$20 | E36: =$B$9*$B$20 | F36: =SUM(B36:E36)
A37: Jul 2025 | B37: =$B$6*$B$21 | C37: =$B$7*$B$21 | D37: =$B$8*$B$21 | E37: =$B$9*$B$21 | F37: =SUM(B37:E37)
A38: Aug 2025 | B38: =$B$6*$B$22 | C38: =$B$7*$B$22 | D38: =$B$8*$B$22 | E38: =$B$9*$B$22 | F38: =SUM(B38:E38)
A39: Sep 2025 | B39: =$B$6*$B$23 | C39: =$B$7*$B$23 | D39: =$B$8*$B$23 | E39: =$B$9*$B$23 | F39: =SUM(B39:E39)
A40: Oct 2025 | B40: =$B$6*$B$24 | C40: =$B$7*$B$24 | D40: =$B$8*$B$24 | E40: =$B$9*$B$24 | F40: =SUM(B40:E40)
A41: Nov 2025 | B41: =$B$6*$B$25 | C41: =$B$7*$B$25 | D41: =$B$8*$B$25 | E41: =$B$9*$B$25 | F41: =SUM(B41:E41)
A42: Dec 2025 | B42: =$B$6*$B$26 | C42: =$B$7*$B$26 | D42: =$B$8*$B$26 | E42: =$B$9*$B$26 | F42: =SUM(B42:E42)

Sheet Report-->
A1: Keystone BenefitTech, Inc.
A2: P&L Reporting & Allocation Model — FY2025
A3: Last Updated: 2026-02-28
A5: EXECUTIVE SUMMARY
B7: FULL YEAR REVENUE | D7: CONTRIBUTION MARGIN % | F7: TOP PRODUCT BY REVENUE
B8: ='P&L - Monthly Trend'!R7 | D8: ='P&L - Monthly Trend'!R10 | F8: iGO
B10: BEST MONTH (REVENUE) | D10: TOTAL COST OF REVENUE | F10: Q4 vs Q1 REVENUE GROWTH
B11: December | D11: ='P&L - Monthly Trend'!R8 | F11: =('P&L - Monthly Trend'!Q7-'P&L - Monthly Trend'!N7)/'P&L - Monthly Trend'!N7
B12: file:///C:\Users\connor.atlee\Downloads\KeystoneBenefitTech_PL_Model.xlsx
B13: TABLE OF CONTENTS
B14: file:///C:\Users\connor.atlee\Downloads\KeystoneBenefitTech_PL_Model.xlsx
B15: Assumptions & Driver Table
B16: Data Dictionary — Products, Departments, Vendors
B17: AWS Cost Allocation Model
B18: P&L Monthly Trend — Consolidated & By Product
B19: Product Line Summary — Revenue & Expenses
B20: Functional P&L — Monthly Trend by Product
B21: Functional P&L Summary — January 2025
B22: Functional P&L Summary — February 2025
B23: Functional P&L Summary — March 2025
... B26: Reconciliation Checks — Model Health

Sheet P&L - Monthly Trend
A1: Keystone BenefitTech, Inc. | R1: Last Updated: 2026-02-28
A2: P&L - Monthly Trend
A4: Line Item | B4: Jan 2025 | C4: Feb 2025 | D4: Mar 2025 | E4: Apr 2025 | F4: May 2025 | G4: Jun 2025 | H4: Jul 2025 | I4: Aug 2025 | J4: Sep 2025 | K4: Oct 2025 | L4: Nov 2025 | M4: Dec 2025 | N4: Q1 2025 | O4: Q2 2025 | P4: Q3 2025 | Q4: Q4 2025 | R4: 2025 Total
A6: Consolidated
A7: Revenue | B7: =B15+B23+B31+B39 | C7: =C15+C23+C31+C39 | D7: =D15+D23+D31+D39 | E7: =E15+E23+E31+E39 | F7: =F15+F23+F31+F39 | G7: =G15+G23+G31+G39 | H7: =H15+H23+H31+H39 | I7: =I15+I23+I31+I39 | ... R7: =R15+R23+R31+R39
A8: Cost of Revenue | B8: =B16+B24+B32+B40 | C8: =C16+C24+C32+C40 | D8: =D16+D24+D32+D40 | E8: =E16+E24+E32+E40 | F8: =F16+F24+F32+F40 | G8: =G16+G24+G32+G40 | H8: =H16+H24+H32+H40 | I8: =I16+I24+I32+I40 | ... R8: =R16+R24+R32+R40
A9: Contribution Margin $ | B9: =B17+B25+B33+B41 | C9: =C17+C25+C33+C41 | D9: =D17+D25+D33+D41 | E9: =E17+E25+E33+E41 | F9: =F17+F25+F33+F41 | G9: =G17+G25+G33+G41 | H9: =H17+H25+H33+H41 | I9: =I17+I25+I33+I41 | ... R9: =R17+R25+R33+R41
A10: Contribution Margin % | B10: =IFERROR(B9/B7,0) | C10: =IFERROR(C9/C7,0) | D10: =IFERROR(D9/D7,0) | E10: =IFERROR(E9/E7,0) | F10: =IFERROR(F9/F7,0) | G10: =IFERROR(G9/G7,0) | H10: =IFERROR(H9/H7,0) | I10: =IFERROR(I9/I7,0) | ... R10: =IFERROR(R9/R7,0)
A11: Contribution Margin + R&D $ | B11: =B19+B27+B35+B43 | C11: =C19+C27+C35+C43 | D11: =D19+D27+D35+D43 | E11: =E19+E27+E35+E43 | F11: =F19+F27+F35+F43 | G11: =G19+G27+G35+G43 | H11: =H19+H27+H35+H43 | I11: =I19+I27+I35+I43 | ... R11: =R19+R27+R35+R43
A12: Contribution Margin + R&D % | B12: =IFERROR(B11/B7,0) | C12: =IFERROR(C11/C7,0) | D12: =IFERROR(D11/D7,0) | E12: =IFERROR(E11/E7,0) | F12: =IFERROR(F11/F7,0) | G12: =IFERROR(G11/G7,0) | H12: =IFERROR(H11/H7,0) | I12: =IFERROR(I11/I7,0) | ... R12: =IFERROR(R11/R7,0)
A14: iGO
A15: Revenue | B15: ='Functional P&L - Monthly Trend'!B11 | C15: ='Functional P&L - Monthly Trend'!C11 | D15: ='Functional P&L - Monthly Trend'!D11 | E15: ='Functional P&L - Monthly Trend'!E11 | F15: ='Functional P&L - Monthly Trend'!F11 | G15: ='Functional P&L - Monthly Trend'!G11 | H15: ='Functional P&L - Monthly Trend'!H11 | I15: ='Functional P&L - Monthly Trend'!I11 | ... R15: ='Functional P&L - Monthly Trend'!R11
A16: Cost of Revenue | B16: ='Functional P&L - Monthly Trend'!B21 | C16: ='Functional P&L - Monthly Trend'!C21 | D16: ='Functional P&L - Monthly Trend'!D21 | E16: ='Functional P&L - Monthly Trend'!E21 | F16: ='Functional P&L - Monthly Trend'!F21 | G16: ='Functional P&L - Monthly Trend'!G21 | H16: ='Functional P&L - Monthly Trend'!H21 | I16: ='Functional P&L - Monthly Trend'!I21 | ... R16: ='Functional P&L - Monthly Trend'!R21
A17: Contribution Margin $ | B17: ='Functional P&L - Monthly Trend'!B25 | C17: ='Functional P&L - Monthly Trend'!C25 | D17: ='Functional P&L - Monthly Trend'!D25 | E17: ='Functional P&L - Monthly Trend'!E25 | F17: ='Functional P&L - Monthly Trend'!F25 | G17: ='Functional P&L - Monthly Trend'!G25 | H17: ='Functional P&L - Monthly Trend'!H25 | I17: ='Functional P&L - Monthly Trend'!I25 | ... R17: ='Functional P&L - Monthly Trend'!R25
A18: Contribution Margin % | B18: ='Functional P&L - Monthly Trend'!B30 | C18: ='Functional P&L - Monthly Trend'!C30 | D18: ='Functional P&L - Monthly Trend'!D30 | E18: ='Functional P&L - Monthly Trend'!E30 | F18: ='Functional P&L - Monthly Trend'!F30 | G18: ='Functional P&L - Monthly Trend'!G30 | H18: ='Functional P&L - Monthly Trend'!H30 | I18: ='Functional P&L - Monthly Trend'!I30 | ... R18: ='Functional P&L - Monthly Trend'!R30
A19: Contribution Margin + R&D $ | B19: ='Functional P&L - Monthly Trend'!B38 | C19: ='Functional P&L - Monthly Trend'!C38 | D19: ='Functional P&L - Monthly Trend'!D38 | E19: ='Functional P&L - Monthly Trend'!E38 | F19: ='Functional P&L - Monthly Trend'!F38 | G19: ='Functional P&L - Monthly Trend'!G38 | H19: ='Functional P&L - Monthly Trend'!H38 | I19: ='Functional P&L - Monthly Trend'!I38 | ... R19: ='Functional P&L - Monthly Trend'!R38
A20: Contribution Margin + R&D % | B20: ='Functional P&L - Monthly Trend'!B39 | C20: ='Functional P&L - Monthly Trend'!C39 | D20: ='Functional P&L - Monthly Trend'!D39 | E20: ='Functional P&L - Monthly Trend'!E39 | F20: ='Functional P&L - Monthly Trend'!F39 | G20: ='Functional P&L - Monthly Trend'!G39 | H20: ='Functional P&L - Monthly Trend'!H39 | I20: ='Functional P&L - Monthly Trend'!I39 | ... R20: ='Functional P&L - Monthly Trend'!R39
A22: Affirm
A23: Revenue | B23: ='Functional P&L - Monthly Trend'!B47 | C23: ='Functional P&L - Monthly Trend'!C47 | D23: ='Functional P&L - Monthly Trend'!D47 | E23: ='Functional P&L - Monthly Trend'!E47 | F23: ='Functional P&L - Monthly Trend'!F47 | G23: ='Functional P&L - Monthly Trend'!G47 | H23: ='Functional P&L - Monthly Trend'!H47 | I23: ='Functional P&L - Monthly Trend'!I47 | ... R23: ='Functional P&L - Monthly Trend'!R47
A24: Cost of Revenue | B24: ='Functional P&L - Monthly Trend'!B57 | C24: ='Functional P&L - Monthly Trend'!C57 | D24: ='Functional P&L - Monthly Trend'!D57 | E24: ='Functional P&L - Monthly Trend'!E57 | F24: ='Functional P&L - Monthly Trend'!F57 | G24: ='Functional P&L - Monthly Trend'!G57 | H24: ='Functional P&L - Monthly Trend'!H57 | I24: ='Functional P&L - Monthly Trend'!I57 | ... R24: ='Functional P&L - Monthly Trend'!R57
A25: Contribution Margin $ | B25: ='Functional P&L - Monthly Trend'!B61 | C25: ='Functional P&L - Monthly Trend'!C61 | D25: ='Functional P&L - Monthly Trend'!D61 | E25: ='Functional P&L - Monthly Trend'!E61 | F25: ='Functional P&L - Monthly Trend'!F61 | G25: ='Functional P&L - Monthly Trend'!G61 | H25: ='Functional P&L - Monthly Trend'!H61 | I25: ='Functional P&L - Monthly Trend'!I61 | ... R25: ='Functional P&L - Monthly Trend'!R61
A26: Contribution Margin % | B26: ='Functional P&L - Monthly Trend'!B66 | C26: ='Functional P&L - Monthly Trend'!C66 | D26: ='Functional P&L - Monthly Trend'!D66 | E26: ='Functional P&L - Monthly Trend'!E66 | F26: ='Functional P&L - Monthly Trend'!F66 | G26: ='Functional P&L - Monthly Trend'!G66 | H26: ='Functional P&L - Monthly Trend'!H66 | I26: ='Functional P&L - Monthly Trend'!I66 | ... R26: ='Functional P&L - Monthly Trend'!R66
A27: Contribution Margin + R&D $ | B27: ='Functional P&L - Monthly Trend'!B74 | C27: ='Functional P&L - Monthly Trend'!C74 | D27: ='Functional P&L - Monthly Trend'!D74 | E27: ='Functional P&L - Monthly Trend'!E74 | F27: ='Functional P&L - Monthly Trend'!F74 | G27: ='Functional P&L - Monthly Trend'!G74 | H27: ='Functional P&L - Monthly Trend'!H74 | I27: ='Functional P&L - Monthly Trend'!I74 | ... R27: ='Functional P&L - Monthly Trend'!R74
A28: Contribution Margin + R&D % | B28: ='Functional P&L - Monthly Trend'!B75 | C28: ='Functional P&L - Monthly Trend'!C75 | D28: ='Functional P&L - Monthly Trend'!D75 | E28: ='Functional P&L - Monthly Trend'!E75 | F28: ='Functional P&L - Monthly Trend'!F75 | G28: ='Functional P&L - Monthly Trend'!G75 | H28: ='Functional P&L - Monthly Trend'!H75 | I28: ='Functional P&L - Monthly Trend'!I75 | ... R28: ='Functional P&L - Monthly Trend'!R75
A30: InsureSight
A31: Revenue | B31: ='Functional P&L - Monthly Trend'!B83 | C31: ='Functional P&L - Monthly Trend'!C83 | D31: ='Functional P&L - Monthly Trend'!D83 | E31: ='Functional P&L - Monthly Trend'!E83 | F31: ='Functional P&L - Monthly Trend'!F83 | G31: ='Functional P&L - Monthly Trend'!G83 | H31: ='Functional P&L - Monthly Trend'!H83 | I31: ='Functional P&L - Monthly Trend'!I83 | ... R31: ='Functional P&L - Monthly Trend'!R83
A32: Cost of Revenue | B32: ='Functional P&L - Monthly Trend'!B93 | C32: ='Functional P&L - Monthly Trend'!C93 | D32: ='Functional P&L - Monthly Trend'!D93 | E32: ='Functional P&L - Monthly Trend'!E93 | F32: ='Functional P&L - Monthly Trend'!F93 | G32: ='Functional P&L - Monthly Trend'!G93 | H32: ='Functional P&L - Monthly Trend'!H93 | I32: ='Functional P&L - Monthly Trend'!I93 | ... R32: ='Functional P&L - Monthly Trend'!R93
A33: Contribution Margin $ | B33: ='Functional P&L - Monthly Trend'!B97 | C33: ='Functional P&L - Monthly Trend'!C97 | D33: ='Functional P&L - Monthly Trend'!D97 | E33: ='Functional P&L - Monthly Trend'!E97 | F33: ='Functional P&L - Monthly Trend'!F97 | G33: ='Functional P&L - Monthly Trend'!G97 | H33: ='Functional P&L - Monthly Trend'!H97 | I33: ='Functional P&L - Monthly Trend'!I97 | ... R33: ='Functional P&L - Monthly Trend'!R97
A34: Contribution Margin % | B34: ='Functional P&L - Monthly Trend'!B102 | C34: ='Functional P&L - Monthly Trend'!C102 | D34: ='Functional P&L - Monthly Trend'!D102 | E34: ='Functional P&L - Monthly Trend'!E102 | F34: ='Functional P&L - Monthly Trend'!F102 | G34: ='Functional P&L - Monthly Trend'!G102 | H34: ='Functional P&L - Monthly Trend'!H102 | I34: ='Functional P&L - Monthly Trend'!I102 | ... R34: ='Functional P&L - Monthly Trend'!R102
A35: Contribution Margin + R&D $ | B35: ='Functional P&L - Monthly Trend'!B110 | C35: ='Functional P&L - Monthly Trend'!C110 | D35: ='Functional P&L - Monthly Trend'!D110 | E35: ='Functional P&L - Monthly Trend'!E110 | F35: ='Functional P&L - Monthly Trend'!F110 | G35: ='Functional P&L - Monthly Trend'!G110 | H35: ='Functional P&L - Monthly Trend'!H110 | I35: ='Functional P&L - Monthly Trend'!I110 | ... R35: ='Functional P&L - Monthly Trend'!R110
A36: Contribution Margin + R&D % | B36: ='Functional P&L - Monthly Trend'!B111 | C36: ='Functional P&L - Monthly Trend'!C111 | D36: ='Functional P&L - Monthly Trend'!D111 | E36: ='Functional P&L - Monthly Trend'!E111 | F36: ='Functional P&L - Monthly Trend'!F111 | G36: ='Functional P&L - Monthly Trend'!G111 | H36: ='Functional P&L - Monthly Trend'!H111 | I36: ='Functional P&L - Monthly Trend'!I111 | ... R36: ='Functional P&L - Monthly Trend'!R111
A38: DocFast
A39: Revenue | B39: ='Functional P&L - Monthly Trend'!B119 | C39: ='Functional P&L - Monthly Trend'!C119 | D39: ='Functional P&L - Monthly Trend'!D119 | E39: ='Functional P&L - Monthly Trend'!E119 | F39: ='Functional P&L - Monthly Trend'!F119 | G39: ='Functional P&L - Monthly Trend'!G119 | H39: ='Functional P&L - Monthly Trend'!H119 | I39: ='Functional P&L - Monthly Trend'!I119 | ... R39: ='Functional P&L - Monthly Trend'!R119
A40: Cost of Revenue | B40: ='Functional P&L - Monthly Trend'!B129 | C40: ='Functional P&L - Monthly Trend'!C129 | D40: ='Functional P&L - Monthly Trend'!D129 | E40: ='Functional P&L - Monthly Trend'!E129 | F40: ='Functional P&L - Monthly Trend'!F129 | G40: ='Functional P&L - Monthly Trend'!G129 | H40: ='Functional P&L - Monthly Trend'!H129 | I40: ='Functional P&L - Monthly Trend'!I129 | ... R40: ='Functional P&L - Monthly Trend'!R129
A41: Contribution Margin $ | B41: ='Functional P&L - Monthly Trend'!B133 | C41: ='Functional P&L - Monthly Trend'!C133 | D41: ='Functional P&L - Monthly Trend'!D133 | E41: ='Functional P&L - Monthly Trend'!E133 | F41: ='Functional P&L - Monthly Trend'!F133 | G41: ='Functional P&L - Monthly Trend'!G133 | H41: ='Functional P&L - Monthly Trend'!H133 | I41: ='Functional P&L - Monthly Trend'!I133 | ... R41: ='Functional P&L - Monthly Trend'!R133
A42: Contribution Margin % | B42: ='Functional P&L - Monthly Trend'!B138 | C42: ='Functional P&L - Monthly Trend'!C138 | D42: ='Functional P&L - Monthly Trend'!D138 | E42: ='Functional P&L - Monthly Trend'!E138 | F42: ='Functional P&L - Monthly Trend'!F138 | G42: ='Functional P&L - Monthly Trend'!G138 | H42: ='Functional P&L - Monthly Trend'!H138 | I42: ='Functional P&L - Monthly Trend'!I138 | ... R42: ='Functional P&L - Monthly Trend'!R138
A43: Contribution Margin + R&D $ | B43: ='Functional P&L - Monthly Trend'!B146 | C43: ='Functional P&L - Monthly Trend'!C146 | D43: ='Functional P&L - Monthly Trend'!D146 | E43: ='Functional P&L - Monthly Trend'!E146 | F43: ='Functional P&L - Monthly Trend'!F146 | G43: ='Functional P&L - Monthly Trend'!G146 | H43: ='Functional P&L - Monthly Trend'!H146 | I43: ='Functional P&L - Monthly Trend'!I146 | ... R43: ='Functional P&L - Monthly Trend'!R146
A44: Contribution Margin + R&D % | B44: ='Functional P&L - Monthly Trend'!B147 | C44: ='Functional P&L - Monthly Trend'!C147 | D44: ='Functional P&L - Monthly Trend'!D147 | E44: ='Functional P&L - Monthly Trend'!E147 | F44: ='Functional P&L - Monthly Trend'!F147 | G44: ='Functional P&L - Monthly Trend'!G147 | H44: ='Functional P&L - Monthly Trend'!H147 | I44: ='Functional P&L - Monthly Trend'!I147 | ... R44: ='Functional P&L - Monthly Trend'!R147

Sheet Product Line Summary
A1: Keystone BenefitTech, Inc. | R1: Last Updated: 2026-02-28
A2: Product Line Summary — FY2025
A4: Line Item | B4: Jan 2025 | C4: Feb 2025 | D4: Mar 2025 | E4: Apr 2025 | F4: May 2025 | G4: Jun 2025 | H4: Jul 2025 | I4: Aug 2025 | J4: Sep 2025 | K4: Oct 2025 | L4: Nov 2025 | M4: Dec 2025 | N4: Q1 2025 | O4: Q2 2025 | P4: Q3 2025 | Q4: Q4 2025 | R4: 2025 Total
A5: SECTION 1: P&L Summary
A7: iGO
A8: Revenue | B8: ='Functional P&L - Monthly Trend'!B11 | C8: ='Functional P&L - Monthly Trend'!C11 | D8: ='Functional P&L - Monthly Trend'!D11 | E8: ='Functional P&L - Monthly Trend'!E11 | F8: ='Functional P&L - Monthly Trend'!F11 | G8: ='Functional P&L - Monthly Trend'!G11 | H8: ='Functional P&L - Monthly Trend'!H11 | I8: ='Functional P&L - Monthly Trend'!I11 | ... R8: ='Functional P&L - Monthly Trend'!R11
A9: Cost of Revenue | B9: ='Functional P&L - Monthly Trend'!B21 | C9: ='Functional P&L - Monthly Trend'!C21 | D9: ='Functional P&L - Monthly Trend'!D21 | E9: ='Functional P&L - Monthly Trend'!E21 | F9: ='Functional P&L - Monthly Trend'!F21 | G9: ='Functional P&L - Monthly Trend'!G21 | H9: ='Functional P&L - Monthly Trend'!H21 | I9: ='Functional P&L - Monthly Trend'!I21 | ... R9: ='Functional P&L - Monthly Trend'!R21
A10: Contribution Margin $ | B10: ='Functional P&L - Monthly Trend'!B25 | C10: ='Functional P&L - Monthly Trend'!C25 | D10: ='Functional P&L - Monthly Trend'!D25 | E10: ='Functional P&L - Monthly Trend'!E25 | F10: ='Functional P&L - Monthly Trend'!F25 | G10: ='Functional P&L - Monthly Trend'!G25 | H10: ='Functional P&L - Monthly Trend'!H25 | I10: ='Functional P&L - Monthly Trend'!I25 | ... R10: ='Functional P&L - Monthly Trend'!R25
A11: Contribution Margin % | B11: ='Functional P&L - Monthly Trend'!B30 | C11: ='Functional P&L - Monthly Trend'!C30 | D11: ='Functional P&L - Monthly Trend'!D30 | E11: ='Functional P&L - Monthly Trend'!E30 | F11: ='Functional P&L - Monthly Trend'!F30 | G11: ='Functional P&L - Monthly Trend'!G30 | H11: ='Functional P&L - Monthly Trend'!H30 | I11: ='Functional P&L - Monthly Trend'!I30 | ... R11: ='Functional P&L - Monthly Trend'!R30
A12: Contribution Margin + R&D $ | B12: ='Functional P&L - Monthly Trend'!B38 | C12: ='Functional P&L - Monthly Trend'!C38 | D12: ='Functional P&L - Monthly Trend'!D38 | E12: ='Functional P&L - Monthly Trend'!E38 | F12: ='Functional P&L - Monthly Trend'!F38 | G12: ='Functional P&L - Monthly Trend'!G38 | H12: ='Functional P&L - Monthly Trend'!H38 | I12: ='Functional P&L - Monthly Trend'!I38 | ... R12: ='Functional P&L - Monthly Trend'!R38
A13: Contribution Margin + R&D % | B13: ='Functional P&L - Monthly Trend'!B39 | C13: ='Functional P&L - Monthly Trend'!C39 | D13: ='Functional P&L - Monthly Trend'!D39 | E13: ='Functional P&L - Monthly Trend'!E39 | F13: ='Functional P&L - Monthly Trend'!F39 | G13: ='Functional P&L - Monthly Trend'!G39 | H13: ='Functional P&L - Monthly Trend'!H39 | I13: ='Functional P&L - Monthly Trend'!I39 | ... R13: ='Functional P&L - Monthly Trend'!R39
A15: Affirm
A16: Revenue | B16: ='Functional P&L - Monthly Trend'!B47 | C16: ='Functional P&L - Monthly Trend'!C47 | D16: ='Functional P&L - Monthly Trend'!D47 | E16: ='Functional P&L - Monthly Trend'!E47 | F16: ='Functional P&L - Monthly Trend'!F47 | G16: ='Functional P&L - Monthly Trend'!G47 | H16: ='Functional P&L - Monthly Trend'!H47 | I16: ='Functional P&L - Monthly Trend'!I47 | ... R16: ='Functional P&L - Monthly Trend'!R47
A17: Cost of Revenue | B17: ='Functional P&L - Monthly Trend'!B57 | C17: ='Functional P&L - Monthly Trend'!C57 | D17: ='Functional P&L - Monthly Trend'!D57 | E17: ='Functional P&L - Monthly Trend'!E57 | F17: ='Functional P&L - Monthly Trend'!F57 | G17: ='Functional P&L - Monthly Trend'!G57 | H17: ='Functional P&L - Monthly Trend'!H57 | I17: ='Functional P&L - Monthly Trend'!I57 | ... R17: ='Functional P&L - Monthly Trend'!R57
A18: Contribution Margin $ | B18: ='Functional P&L - Monthly Trend'!B61 | C18: ='Functional P&L - Monthly Trend'!C61 | D18: ='Functional P&L - Monthly Trend'!D61 | E18: ='Functional P&L - Monthly Trend'!E61 | F18: ='Functional P&L - Monthly Trend'!F61 | G18: ='Functional P&L - Monthly Trend'!G61 | H18: ='Functional P&L - Monthly Trend'!H61 | I18: ='Functional P&L - Monthly Trend'!I61 | ... R18: ='Functional P&L - Monthly Trend'!R61
A19: Contribution Margin % | B19: ='Functional P&L - Monthly Trend'!B66 | C19: ='Functional P&L - Monthly Trend'!C66 | D19: ='Functional P&L - Monthly Trend'!D66 | E19: ='Functional P&L - Monthly Trend'!E66 | F19: ='Functional P&L - Monthly Trend'!F66 | G19: ='Functional P&L - Monthly Trend'!G66 | H19: ='Functional P&L - Monthly Trend'!H66 | I19: ='Functional P&L - Monthly Trend'!I66 | ... R19: ='Functional P&L - Monthly Trend'!R66
A20: Contribution Margin + R&D $ | B20: ='Functional P&L - Monthly Trend'!B74 | C20: ='Functional P&L - Monthly Trend'!C74 | D20: ='Functional P&L - Monthly Trend'!D74 | E20: ='Functional P&L - Monthly Trend'!E74 | F20: ='Functional P&L - Monthly Trend'!F74 | G20: ='Functional P&L - Monthly Trend'!G74 | H20: ='Functional P&L - Monthly Trend'!H74 | I20: ='Functional P&L - Monthly Trend'!I74 | ... R20: ='Functional P&L - Monthly Trend'!R74
A21: Contribution Margin + R&D % | B21: ='Functional P&L - Monthly Trend'!B75 | C21: ='Functional P&L - Monthly Trend'!C75 | D21: ='Functional P&L - Monthly Trend'!D75 | E21: ='Functional P&L - Monthly Trend'!E75 | F21: ='Functional P&L - Monthly Trend'!F75 | G21: ='Functional P&L - Monthly Trend'!G75 | H21: ='Functional P&L - Monthly Trend'!H75 | I21: ='Functional P&L - Monthly Trend'!I75 | ... R21: ='Functional P&L - Monthly Trend'!R75
A23: Insuresight
A24: Revenue | B24: ='Functional P&L - Monthly Trend'!B83 | C24: ='Functional P&L - Monthly Trend'!C83 | D24: ='Functional P&L - Monthly Trend'!D83 | E24: ='Functional P&L - Monthly Trend'!E83 | F24: ='Functional P&L - Monthly Trend'!F83 | G24: ='Functional P&L - Monthly Trend'!G83 | H24: ='Functional P&L - Monthly Trend'!H83 | I24: ='Functional P&L - Monthly Trend'!I83 | ... R24: ='Functional P&L - Monthly Trend'!R83
A25: Cost of Revenue | B25: ='Functional P&L - Monthly Trend'!B93 | C25: ='Functional P&L - Monthly Trend'!C93 | D25: ='Functional P&L - Monthly Trend'!D93 | E25: ='Functional P&L - Monthly Trend'!E93 | F25: ='Functional P&L - Monthly Trend'!F93 | G25: ='Functional P&L - Monthly Trend'!G93 | H25: ='Functional P&L - Monthly Trend'!H93 | I25: ='Functional P&L - Monthly Trend'!I93 | ... R25: ='Functional P&L - Monthly Trend'!R93
A26: Contribution Margin $ | B26: ='Functional P&L - Monthly Trend'!B97 | C26: ='Functional P&L - Monthly Trend'!C97 | D26: ='Functional P&L - Monthly Trend'!D97 | E26: ='Functional P&L - Monthly Trend'!E97 | F26: ='Functional P&L - Monthly Trend'!F97 | G26: ='Functional P&L - Monthly Trend'!G97 | H26: ='Functional P&L - Monthly Trend'!H97 | I26: ='Functional P&L - Monthly Trend'!I97 | ... R26: ='Functional P&L - Monthly Trend'!R97
A27: Contribution Margin % | B27: ='Functional P&L - Monthly Trend'!B102 | C27: ='Functional P&L - Monthly Trend'!C102 | D27: ='Functional P&L - Monthly Trend'!D102 | E27: ='Functional P&L - Monthly Trend'!E102 | F27: ='Functional P&L - Monthly Trend'!F102 | G27: ='Functional P&L - Monthly Trend'!G102 | H27: ='Functional P&L - Monthly Trend'!H102 | I27: ='Functional P&L - Monthly Trend'!I102 | ... R27: ='Functional P&L - Monthly Trend'!R102
A28: Contribution Margin + R&D $ | B28: ='Functional P&L - Monthly Trend'!B110 | C28: ='Functional P&L - Monthly Trend'!C110 | D28: ='Functional P&L - Monthly Trend'!D110 | E28: ='Functional P&L - Monthly Trend'!E110 | F28: ='Functional P&L - Monthly Trend'!F110 | G28: ='Functional P&L - Monthly Trend'!G110 | H28: ='Functional P&L - Monthly Trend'!H110 | I28: ='Functional P&L - Monthly Trend'!I110 | ... R28: ='Functional P&L - Monthly Trend'!R110
A29: Contribution Margin + R&D % | B29: ='Functional P&L - Monthly Trend'!B111 | C29: ='Functional P&L - Monthly Trend'!C111 | D29: ='Functional P&L - Monthly Trend'!D111 | E29: ='Functional P&L - Monthly Trend'!E111 | F29: ='Functional P&L - Monthly Trend'!F111 | G29: ='Functional P&L - Monthly Trend'!G111 | H29: ='Functional P&L - Monthly Trend'!H111 | I29: ='Functional P&L - Monthly Trend'!I111 | ... R29: ='Functional P&L - Monthly Trend'!R111
A31: DocFast
A32: Revenue | B32: ='Functional P&L - Monthly Trend'!B119 | C32: ='Functional P&L - Monthly Trend'!C119 | D32: ='Functional P&L - Monthly Trend'!D119 | E32: ='Functional P&L - Monthly Trend'!E119 | F32: ='Functional P&L - Monthly Trend'!F119 | G32: ='Functional P&L - Monthly Trend'!G119 | H32: ='Functional P&L - Monthly Trend'!H119 | I32: ='Functional P&L - Monthly Trend'!I119 | ... R32: ='Functional P&L - Monthly Trend'!R119
A33: Cost of Revenue | B33: ='Functional P&L - Monthly Trend'!B129 | C33: ='Functional P&L - Monthly Trend'!C129 | D33: ='Functional P&L - Monthly Trend'!D129 | E33: ='Functional P&L - Monthly Trend'!E129 | F33: ='Functional P&L - Monthly Trend'!F129 | G33: ='Functional P&L - Monthly Trend'!G129 | H33: ='Functional P&L - Monthly Trend'!H129 | I33: ='Functional P&L - Monthly Trend'!I129 | ... R33: ='Functional P&L - Monthly Trend'!R129
A34: Contribution Margin $ | B34: ='Functional P&L - Monthly Trend'!B133 | C34: ='Functional P&L - Monthly Trend'!C133 | D34: ='Functional P&L - Monthly Trend'!D133 | E34: ='Functional P&L - Monthly Trend'!E133 | F34: ='Functional P&L - Monthly Trend'!F133 | G34: ='Functional P&L - Monthly Trend'!G133 | H34: ='Functional P&L - Monthly Trend'!H133 | I34: ='Functional P&L - Monthly Trend'!I133 | ... R34: ='Functional P&L - Monthly Trend'!R133
A35: Contribution Margin % | B35: ='Functional P&L - Monthly Trend'!B138 | C35: ='Functional P&L - Monthly Trend'!C138 | D35: ='Functional P&L - Monthly Trend'!D138 | E35: ='Functional P&L - Monthly Trend'!E138 | F35: ='Functional P&L - Monthly Trend'!F138 | G35: ='Functional P&L - Monthly Trend'!G138 | H35: ='Functional P&L - Monthly Trend'!H138 | I35: ='Functional P&L - Monthly Trend'!I138 | ... R35: ='Functional P&L - Monthly Trend'!R138
A36: Contribution Margin + R&D $ | B36: ='Functional P&L - Monthly Trend'!B146 | C36: ='Functional P&L - Monthly Trend'!C146 | D36: ='Functional P&L - Monthly Trend'!D146 | E36: ='Functional P&L - Monthly Trend'!E146 | F36: ='Functional P&L - Monthly Trend'!F146 | G36: ='Functional P&L - Monthly Trend'!G146 | H36: ='Functional P&L - Monthly Trend'!H146 | I36: ='Functional P&L - Monthly Trend'!I146 | ... R36: ='Functional P&L - Monthly Trend'!R146
A37: Contribution Margin + R&D % | B37: ='Functional P&L - Monthly Trend'!B147 | C37: ='Functional P&L - Monthly Trend'!C147 | D37: ='Functional P&L - Monthly Trend'!D147 | E37: ='Functional P&L - Monthly Trend'!E147 | F37: ='Functional P&L - Monthly Trend'!F147 | G37: ='Functional P&L - Monthly Trend'!G147 | H37: ='Functional P&L - Monthly Trend'!H147 | I37: ='Functional P&L - Monthly Trend'!I147 | ... R37: ='Functional P&L - Monthly Trend'!R147
A40: SECTION 2: Expenses by Department
A42: iGO
A43: NetOps | B43: ='Functional P&L - Monthly Trend'!B14 | C43: ='Functional P&L - Monthly Trend'!C14 | D43: ='Functional P&L - Monthly Trend'!D14 | E43: ='Functional P&L - Monthly Trend'!E14 | F43: ='Functional P&L - Monthly Trend'!F14 | G43: ='Functional P&L - Monthly Trend'!G14 | H43: ='Functional P&L - Monthly Trend'!H14 | I43: ='Functional P&L - Monthly Trend'!I14 | ... R43: ='Functional P&L - Monthly Trend'!R14
A44: Security | B44: ='Functional P&L - Monthly Trend'!B15 | C44: ='Functional P&L - Monthly Trend'!C15 | D44: ='Functional P&L - Monthly Trend'!D15 | E44: ='Functional P&L - Monthly Trend'!E15 | F44: ='Functional P&L - Monthly Trend'!F15 | G44: ='Functional P&L - Monthly Trend'!G15 | H44: ='Functional P&L - Monthly Trend'!H15 | I44: ='Functional P&L - Monthly Trend'!I15 | ... R44: ='Functional P&L - Monthly Trend'!R15
A45: Support | B45: ='Functional P&L - Monthly Trend'!B16 | C45: ='Functional P&L - Monthly Trend'!C16 | D45: ='Functional P&L - Monthly Trend'!D16 | E45: ='Functional P&L - Monthly Trend'!E16 | F45: ='Functional P&L - Monthly Trend'!F16 | G45: ='Functional P&L - Monthly Trend'!G16 | H45: ='Functional P&L - Monthly Trend'!H16 | I45: ='Functional P&L - Monthly Trend'!I16 | ... R45: ='Functional P&L - Monthly Trend'!R16
A46: Partners | B46: ='Functional P&L - Monthly Trend'!B17 | C46: ='Functional P&L - Monthly Trend'!C17 | D46: ='Functional P&L - Monthly Trend'!D17 | E46: ='Functional P&L - Monthly Trend'!E17 | F46: ='Functional P&L - Monthly Trend'!F17 | G46: ='Functional P&L - Monthly Trend'!G17 | H46: ='Functional P&L - Monthly Trend'!H17 | I46: ='Functional P&L - Monthly Trend'!I17 | ... R46: ='Functional P&L - Monthly Trend'!R17
A47: Content | B47: ='Functional P&L - Monthly Trend'!B18 | C47: ='Functional P&L - Monthly Trend'!C18 | D47: ='Functional P&L - Monthly Trend'!D18 | E47: ='Functional P&L - Monthly Trend'!E18 | F47: ='Functional P&L - Monthly Trend'!F18 | G47: ='Functional P&L - Monthly Trend'!G18 | H47: ='Functional P&L - Monthly Trend'!H18 | I47: ='Functional P&L - Monthly Trend'!I18 | ... R47: ='Functional P&L - Monthly Trend'!R18
A48: Research & Development | B48: ='Functional P&L - Monthly Trend'!B33 | C48: ='Functional P&L - Monthly Trend'!C33 | D48: ='Functional P&L - Monthly Trend'!D33 | E48: ='Functional P&L - Monthly Trend'!E33 | F48: ='Functional P&L - Monthly Trend'!F33 | G48: ='Functional P&L - Monthly Trend'!G33 | H48: ='Functional P&L - Monthly Trend'!H33 | I48: ='Functional P&L - Monthly Trend'!I33 | ... R48: ='Functional P&L - Monthly Trend'!R33
A49: Product Management | B49: ='Functional P&L - Monthly Trend'!B36 | C49: ='Functional P&L - Monthly Trend'!C36 | D49: ='Functional P&L - Monthly Trend'!D36 | E49: ='Functional P&L - Monthly Trend'!E36 | F49: ='Functional P&L - Monthly Trend'!F36 | G49: ='Functional P&L - Monthly Trend'!G36 | H49: ='Functional P&L - Monthly Trend'!H36 | I49: ='Functional P&L - Monthly Trend'!I36 | ... R49: ='Functional P&L - Monthly Trend'!R36
A50: Total Expenses | B50: =SUM(B43:B49) | C50: =SUM(C43:C49) | D50: =SUM(D43:D49) | E50: =SUM(E43:E49) | F50: =SUM(F43:F49) | G50: =SUM(G43:G49) | H50: =SUM(H43:H49) | I50: =SUM(I43:I49) | ... R50: =SUM(R43:R49)
A52: Affirm
A53: NetOps | B53: ='Functional P&L - Monthly Trend'!B50 | C53: ='Functional P&L - Monthly Trend'!C50 | D53: ='Functional P&L - Monthly Trend'!D50 | E53: ='Functional P&L - Monthly Trend'!E50 | F53: ='Functional P&L - Monthly Trend'!F50 | G53: ='Functional P&L - Monthly Trend'!G50 | H53: ='Functional P&L - Monthly Trend'!H50 | I53: ='Functional P&L - Monthly Trend'!I50 | ... R53: ='Functional P&L - Monthly Trend'!R50
A54: Security | B54: ='Functional P&L - Monthly Trend'!B51 | C54: ='Functional P&L - Monthly Trend'!C51 | D54: ='Functional P&L - Monthly Trend'!D51 | E54: ='Functional P&L - Monthly Trend'!E51 | F54: ='Functional P&L - Monthly Trend'!F51 | G54: ='Functional P&L - Monthly Trend'!G51 | H54: ='Functional P&L - Monthly Trend'!H51 | I54: ='Functional P&L - Monthly Trend'!I51 | ... R54: ='Functional P&L - Monthly Trend'!R51
A55: Support | B55: ='Functional P&L - Monthly Trend'!B52 | C55: ='Functional P&L - Monthly Trend'!C52 | D55: ='Functional P&L - Monthly Trend'!D52 | E55: ='Functional P&L - Monthly Trend'!E52 | F55: ='Functional P&L - Monthly Trend'!F52 | G55: ='Functional P&L - Monthly Trend'!G52 | H55: ='Functional P&L - Monthly Trend'!H52 | I55: ='Functional P&L - Monthly Trend'!I52 | ... R55: ='Functional P&L - Monthly Trend'!R52
A56: Partners | B56: ='Functional P&L - Monthly Trend'!B53 | C56: ='Functional P&L - Monthly Trend'!C53 | D56: ='Functional P&L - Monthly Trend'!D53 | E56: ='Functional P&L - Monthly Trend'!E53 | F56: ='Functional P&L - Monthly Trend'!F53 | G56: ='Functional P&L - Monthly Trend'!G53 | H56: ='Functional P&L - Monthly Trend'!H53 | I56: ='Functional P&L - Monthly Trend'!I53 | ... R56: ='Functional P&L - Monthly Trend'!R53
A57: Content | B57: ='Functional P&L - Monthly Trend'!B54 | C57: ='Functional P&L - Monthly Trend'!C54 | D57: ='Functional P&L - Monthly Trend'!D54 | E57: ='Functional P&L - Monthly Trend'!E54 | F57: ='Functional P&L - Monthly Trend'!F54 | G57: ='Functional P&L - Monthly Trend'!G54 | H57: ='Functional P&L - Monthly Trend'!H54 | I57: ='Functional P&L - Monthly Trend'!I54 | ... R57: ='Functional P&L - Monthly Trend'!R54
A58: Research & Development | B58: ='Functional P&L - Monthly Trend'!B69 | C58: ='Functional P&L - Monthly Trend'!C69 | D58: ='Functional P&L - Monthly Trend'!D69 | E58: ='Functional P&L - Monthly Trend'!E69 | F58: ='Functional P&L - Monthly Trend'!F69 | G58: ='Functional P&L - Monthly Trend'!G69 | H58: ='Functional P&L - Monthly Trend'!H69 | I58: ='Functional P&L - Monthly Trend'!I69 | ... R58: ='Functional P&L - Monthly Trend'!R69
A59: Product Management | B59: ='Functional P&L - Monthly Trend'!B72 | C59: ='Functional P&L - Monthly Trend'!C72 | D59: ='Functional P&L - Monthly Trend'!D72 | E59: ='Functional P&L - Monthly Trend'!E72 | F59: ='Functional P&L - Monthly Trend'!F72 | G59: ='Functional P&L - Monthly Trend'!G72 | H59: ='Functional P&L - Monthly Trend'!H72 | I59: ='Functional P&L - Monthly Trend'!I72 | ... R59: ='Functional P&L - Monthly Trend'!R72
A60: Total Expenses | B60: =SUM(B53:B59) | C60: =SUM(C53:C59) | D60: =SUM(D53:D59) | E60: =SUM(E53:E59) | F60: =SUM(F53:F59) | G60: =SUM(G53:G59) | H60: =SUM(H53:H59) | I60: =SUM(I53:I59) | ... R60: =SUM(R53:R59)
A62: InsureSight
A63: NetOps | B63: ='Functional P&L - Monthly Trend'!B86 | C63: ='Functional P&L - Monthly Trend'!C86 | D63: ='Functional P&L - Monthly Trend'!D86 | E63: ='Functional P&L - Monthly Trend'!E86 | F63: ='Functional P&L - Monthly Trend'!F86 | G63: ='Functional P&L - Monthly Trend'!G86 | H63: ='Functional P&L - Monthly Trend'!H86 | I63: ='Functional P&L - Monthly Trend'!I86 | ... R63: ='Functional P&L - Monthly Trend'!R86
A64: Security | B64: ='Functional P&L - Monthly Trend'!B87 | C64: ='Functional P&L - Monthly Trend'!C87 | D64: ='Functional P&L - Monthly Trend'!D87 | E64: ='Functional P&L - Monthly Trend'!E87 | F64: ='Functional P&L - Monthly Trend'!F87 | G64: ='Functional P&L - Monthly Trend'!G87 | H64: ='Functional P&L - Monthly Trend'!H87 | I64: ='Functional P&L - Monthly Trend'!I87 | ... R64: ='Functional P&L - Monthly Trend'!R87
A65: Support | B65: ='Functional P&L - Monthly Trend'!B88 | C65: ='Functional P&L - Monthly Trend'!C88 | D65: ='Functional P&L - Monthly Trend'!D88 | E65: ='Functional P&L - Monthly Trend'!E88 | F65: ='Functional P&L - Monthly Trend'!F88 | G65: ='Functional P&L - Monthly Trend'!G88 | H65: ='Functional P&L - Monthly Trend'!H88 | I65: ='Functional P&L - Monthly Trend'!I88 | ... R65: ='Functional P&L - Monthly Trend'!R88
A66: Partners | B66: ='Functional P&L - Monthly Trend'!B89 | C66: ='Functional P&L - Monthly Trend'!C89 | D66: ='Functional P&L - Monthly Trend'!D89 | E66: ='Functional P&L - Monthly Trend'!E89 | F66: ='Functional P&L - Monthly Trend'!F89 | G66: ='Functional P&L - Monthly Trend'!G89 | H66: ='Functional P&L - Monthly Trend'!H89 | I66: ='Functional P&L - Monthly Trend'!I89 | ... R66: ='Functional P&L - Monthly Trend'!R89
A67: Content | B67: ='Functional P&L - Monthly Trend'!B90 | C67: ='Functional P&L - Monthly Trend'!C90 | D67: ='Functional P&L - Monthly Trend'!D90 | E67: ='Functional P&L - Monthly Trend'!E90 | F67: ='Functional P&L - Monthly Trend'!F90 | G67: ='Functional P&L - Monthly Trend'!G90 | H67: ='Functional P&L - Monthly Trend'!H90 | I67: ='Functional P&L - Monthly Trend'!I90 | ... R67: ='Functional P&L - Monthly Trend'!R90
A68: Research & Development | B68: ='Functional P&L - Monthly Trend'!B105 | C68: ='Functional P&L - Monthly Trend'!C105 | D68: ='Functional P&L - Monthly Trend'!D105 | E68: ='Functional P&L - Monthly Trend'!E105 | F68: ='Functional P&L - Monthly Trend'!F105 | G68: ='Functional P&L - Monthly Trend'!G105 | H68: ='Functional P&L - Monthly Trend'!H105 | I68: ='Functional P&L - Monthly Trend'!I105 | ... R68: ='Functional P&L - Monthly Trend'!R105
A69: Product Management | B69: ='Functional P&L - Monthly Trend'!B108 | C69: ='Functional P&L - Monthly Trend'!C108 | D69: ='Functional P&L - Monthly Trend'!D108 | E69: ='Functional P&L - Monthly Trend'!E108 | F69: ='Functional P&L - Monthly Trend'!F108 | G69: ='Functional P&L - Monthly Trend'!G108 | H69: ='Functional P&L - Monthly Trend'!H108 | I69: ='Functional P&L - Monthly Trend'!I108 | ... R69: ='Functional P&L - Monthly Trend'!R108
A70: Total Expenses | B70: =SUM(B63:B69) | C70: =SUM(C63:C69) | D70: =SUM(D63:D69) | E70: =SUM(E63:E69) | F70: =SUM(F63:F69) | G70: =SUM(G63:G69) | H70: =SUM(H63:H69) | I70: =SUM(I63:I69) | ... R70: =SUM(R63:R69)
A72: DocFast
A73: NetOps | B73: ='Functional P&L - Monthly Trend'!B122 | C73: ='Functional P&L - Monthly Trend'!C122 | D73: ='Functional P&L - Monthly Trend'!D122 | E73: ='Functional P&L - Monthly Trend'!E122 | F73: ='Functional P&L - Monthly Trend'!F122 | G73: ='Functional P&L - Monthly Trend'!G122 | H73: ='Functional P&L - Monthly Trend'!H122 | I73: ='Functional P&L - Monthly Trend'!I122 | ... R73: ='Functional P&L - Monthly Trend'!R122
A74: Security | B74: ='Functional P&L - Monthly Trend'!B123 | C74: ='Functional P&L - Monthly Trend'!C123 | D74: ='Functional P&L - Monthly Trend'!D123 | E74: ='Functional P&L - Monthly Trend'!E123 | F74: ='Functional P&L - Monthly Trend'!F123 | G74: ='Functional P&L - Monthly Trend'!G123 | H74: ='Functional P&L - Monthly Trend'!H123 | I74: ='Functional P&L - Monthly Trend'!I123 | ... R74: ='Functional P&L - Monthly Trend'!R123
A75: Support | B75: ='Functional P&L - Monthly Trend'!B124 | C75: ='Functional P&L - Monthly Trend'!C124 | D75: ='Functional P&L - Monthly Trend'!D124 | E75: ='Functional P&L - Monthly Trend'!E124 | F75: ='Functional P&L - Monthly Trend'!F124 | G75: ='Functional P&L - Monthly Trend'!G124 | H75: ='Functional P&L - Monthly Trend'!H124 | I75: ='Functional P&L - Monthly Trend'!I124 | ... R75: ='Functional P&L - Monthly Trend'!R124
A76: Partners | B76: ='Functional P&L - Monthly Trend'!B125 | C76: ='Functional P&L - Monthly Trend'!C125 | D76: ='Functional P&L - Monthly Trend'!D125 | E76: ='Functional P&L - Monthly Trend'!E125 | F76: ='Functional P&L - Monthly Trend'!F125 | G76: ='Functional P&L - Monthly Trend'!G125 | H76: ='Functional P&L - Monthly Trend'!H125 | I76: ='Functional P&L - Monthly Trend'!I125 | ... R76: ='Functional P&L - Monthly Trend'!R125
A77: Content | B77: ='Functional P&L - Monthly Trend'!B126 | C77: ='Functional P&L - Monthly Trend'!C126 | D77: ='Functional P&L - Monthly Trend'!D126 | E77: ='Functional P&L - Monthly Trend'!E126 | F77: ='Functional P&L - Monthly Trend'!F126 | G77: ='Functional P&L - Monthly Trend'!G126 | H77: ='Functional P&L - Monthly Trend'!H126 | I77: ='Functional P&L - Monthly Trend'!I126 | ... R77: ='Functional P&L - Monthly Trend'!R126
A78: Research & Development | B78: ='Functional P&L - Monthly Trend'!B141 | C78: ='Functional P&L - Monthly Trend'!C141 | D78: ='Functional P&L - Monthly Trend'!D141 | E78: ='Functional P&L - Monthly Trend'!E141 | F78: ='Functional P&L - Monthly Trend'!F141 | G78: ='Functional P&L - Monthly Trend'!G141 | H78: ='Functional P&L - Monthly Trend'!H141 | I78: ='Functional P&L - Monthly Trend'!I141 | ... R78: ='Functional P&L - Monthly Trend'!R141
A79: Product Management | B79: ='Functional P&L - Monthly Trend'!B144 | C79: ='Functional P&L - Monthly Trend'!C144 | D79: ='Functional P&L - Monthly Trend'!D144 | E79: ='Functional P&L - Monthly Trend'!E144 | F79: ='Functional P&L - Monthly Trend'!F144 | G79: ='Functional P&L - Monthly Trend'!G144 | H79: ='Functional P&L - Monthly Trend'!H144 | I79: ='Functional P&L - Monthly Trend'!I144 | ... R79: ='Functional P&L - Monthly Trend'!R144
A80: Total Expenses | B80: =SUM(B73:B79) | C80: =SUM(C73:C79) | D80: =SUM(D73:D79) | E80: =SUM(E73:E79) | F80: =SUM(F73:F79) | G80: =SUM(G73:G79) | H80: =SUM(H73:H79) | I80: =SUM(I73:I79) | ... R80: =SUM(R73:R79)

Sheet Functional P&L - Monthly Trend
A1: Keystone BenefitTech, Inc. | R1: Last Updated: 2026-02-28
A2: Functional P&L - Monthly Trend
A4: Line Item | B4: Jan 2025 | C4: Feb 2025 | D4: Mar 2025 | E4: Apr 2025 | F4: May 2025 | G4: Jun 2025 | H4: Jul 2025 | I4: Aug 2025 | J4: Sep 2025 | K4: Oct 2025 | L4: Nov 2025 | M4: Dec 2025 | N4: Q1 2025 | O4: Q2 2025 | P4: Q3 2025 | Q4: Q4 2025 | R4: 2025 Total
A6: iGO
A7: Revenue
A8: Subscription | B8: 4040.8 | C8: 4245.3 | D8: 4346.38 | E8: 4387.97 | F8: 4232.75 | G8: 4490.3 | H8: 4509.14 | I8: 4704.67 | J8: 4511.68 | K8: 4896.07 | L8: 5126.58 | M8: 5003.52 | N8: =SUM(B8:D8) | O8: =SUM(E8:G8) | P8: =SUM(H8:J8) | Q8: =SUM(K8:M8) | R8: =SUM(B8:M8)
A9: Transactions | B9: 1010.1 | C9: 880.75 | D9: 904.62 | E9: 1045.58 | F9: 997.55 | G9: 921.82 | H9: 1007.2 | I9: 1047.57 | J9: 1007.15 | K9: 1253.63 | L9: 1213.96 | M9: 1022.47 | N9: =SUM(B9:D9) | O9: =SUM(E9:G9) | P9: =SUM(H9:J9) | Q9: =SUM(K9:M9) | R9: =SUM(B9:M9)
A10: Services | B10: 317.61 | C10: 360.3 | D10: 505.57 | E10: 223.73 | F10: 451.84 | G10: 492.68 | H10: 353.98 | I10: 366.22 | J10: 661.31 | K10: 548.31 | L10: 283.49 | M10: 686.76 | N10: =SUM(B10:D10) | O10: =SUM(E10:G10) | P10: =SUM(H10:J10) | Q10: =SUM(K10:M10) | R10: =SUM(B10:M10)
A11: Revenue | B11: =B8+B9+B10 | C11: =C8+C9+C10 | D11: =D8+D9+D10 | E11: =E8+E9+E10 | F11: =F8+F9+F10 | G11: =G8+G9+G10 | H11: =H8+H9+H10 | I11: =I8+I9+I10 | ... M11: =M8+M9+M10 | N11: =SUM(B11:D11) | O11: =SUM(E11:G11) | P11: =SUM(H11:J11) | Q11: =SUM(K11:M11) | R11: =SUM(B11:M11)
A13: Cost of Revenue
A14: NetOps | B14: 726.3 | C14: 742.28 | D14: 774.61 | E14: 754.97 | F14: 752.67 | G14: 847.48 | H14: 792.59 | I14: 870.9 | J14: 808.45 | K14: 874.51 | L14: 964.98 | M14: 945.25 | N14: =SUM(B14:D14) | O14: =SUM(E14:G14) | P14: =SUM(H14:J14) | Q14: =SUM(K14:M14) | R14: =SUM(B14:M14)
A15: Security | B15: 162.53 | C15: 173.52 | D15: 167.85 | E15: 171.95 | F15: 177.25 | G15: 181.03 | H15: 181.13 | I15: 192.85 | J15: 172.48 | K15: 197.49 | L15: 205.12 | M15: 207.2 | N15: =SUM(B15:D15) | O15: =SUM(E15:G15) | P15: =SUM(H15:J15) | Q15: =SUM(K15:M15) | R15: =SUM(B15:M15)
A16: Support | B16: 234.14 | C16: 266.45 | D16: 249.83 | E16: 255.01 | F16: 256.38 | G16: 274.14 | H16: 263.38 | I16: 271.55 | J16: 281.27 | K16: 286.31 | L16: 310.5 | M16: 303.8 | N16: =SUM(B16:D16) | O16: =SUM(E16:G16) | P16: =SUM(H16:J16) | Q16: =SUM(K16:M16) | R16: =SUM(B16:M16)
A17: Partners | B17: 120.24 | C17: 128.42 | D17: 130.69 | E17: 137.36 | F17: 123.23 | G17: 137.62 | H17: 131.74 | I17: 139.67 | J17: 137.67 | K17: 143.94 | L17: 150.97 | M17: 153.89 | N17: =SUM(B17:D17) | O17: =SUM(E17:G17) | P17: =SUM(H17:J17) | Q17: =SUM(K17:M17) | R17: =SUM(B17:M17)
A18: Content | B18: 19.34 | C18: 21.14 | D18: 22.82 | E18: 23.03 | F18: 20.26 | G18: 21.81 | H18: 22.02 | I18: 24.54 | J18: 23.42 | K18: 25.41 | L18: 25.3 | M18: 24.16 | N18: =SUM(B18:D18) | O18: =SUM(E18:G18) | P18: =SUM(H18:J18) | Q18: =SUM(K18:M18) | R18: =SUM(B18:M18)
A19: Cost of Subscription | B19: =SUM(B14:B18) | C19: =SUM(C14:C18) | D19: =SUM(D14:D18) | E19: =SUM(E14:E18) | F19: =SUM(F14:F18) | G19: =SUM(G14:G18) | H19: =SUM(H14:H18) | I19: =SUM(I14:I18) | ... M19: =SUM(M14:M18) | N19: =SUM(B19:D19) | O19: =SUM(E19:G19) | P19: =SUM(H19:J19) | Q19: =SUM(K19:M19) | R19: =SUM(B19:M19)
A20: Cost of Services | B20: 186.35 | C20: 204.27 | D20: 287.15 | E20: 113.38 | F20: 259.33 | G20: 270.35 | H20: 191.71 | I20: 206.94 | J20: 358.46 | K20: 325.93 | L20: 144.95 | M20: 400.09 | N20: =SUM(B20:D20) | O20: =SUM(E20:G20) | P20: =SUM(H20:J20) | Q20: =SUM(K20:M20) | R20: =SUM(B20:M20)
A21: Cost of Revenue | B21: =B19+B20 | C21: =C19+C20 | D21: =D19+D20 | E21: =E19+E20 | F21: =F19+F20 | G21: =G19+G20 | H21: =H19+H20 | I21: =I19+I20 | ... M21: =M19+M20 | N21: =SUM(B21:D21) | O21: =SUM(E21:G21) | P21: =SUM(H21:J21) | Q21: =SUM(K21:M21) | R21: =SUM(B21:M21)
A23: Subscriptions Contribution | B23: =B8-B19 | C23: =C8-C19 | D23: =D8-D19 | E23: =E8-E19 | F23: =F8-F19 | G23: =G8-G19 | H23: =H8-H19 | I23: =I8-I19 | ... M23: =M8-M19 | N23: =SUM(B23:D23) | O23: =SUM(E23:G23) | P23: =SUM(H23:J23) | Q23: =SUM(K23:M23) | R23: =SUM(B23:M23)
A24: Services Contribution | B24: =B10-B20 | C24: =C10-C20 | D24: =D10-D20 | E24: =E10-E20 | F24: =F10-F20 | G24: =G10-G20 | H24: =H10-H20 | I24: =I10-I20 | ... M24: =M10-M20 | N24: =SUM(B24:D24) | O24: =SUM(E24:G24) | P24: =SUM(H24:J24) | Q24: =SUM(K24:M24) | R24: =SUM(B24:M24)
A25: Contribution Margin | B25: =B23+B24 | C25: =C23+C24 | D25: =D23+D24 | E25: =E23+E24 | F25: =F23+F24 | G25: =G23+G24 | H25: =H23+H24 | I25: =I23+I24 | ... M25: =M23+M24 | N25: =SUM(B25:D25) | O25: =SUM(E25:G25) | P25: =SUM(H25:J25) | Q25: =SUM(K25:M25) | R25: =SUM(B25:M25)
A26: D&A | B26: 53.69 | C26: 54.86 | D26: 57.57 | E26: 56.57 | F26: 56.82 | G26: 59.05 | H26: 58.7 | I26: 61.18 | J26: 61.8 | K26: 66.98 | L26: 66.24 | M26: 67.13 | N26: =SUM(B26:D26) | O26: =SUM(E26:G26) | P26: =SUM(H26:J26) | Q26: =SUM(K26:M26) | R26: =SUM(B26:M26)
A27: Contribution Margin GAAP | B27: =B25-B26 | C27: =C25-C26 | D27: =D25-D26 | E27: =E25-E26 | F27: =F25-F26 | G27: =G25-G26 | H27: =H25-H26 | I27: =I25-I26 | ... M27: =M25-M26 | N27: =SUM(B27:D27) | O27: =SUM(E27:G27) | P27: =SUM(H27:J27) | Q27: =SUM(K27:M27) | R27: =SUM(B27:M27)
A28: Subscription Margin % | B28: =IFERROR(B23/B8,0) | C28: =IFERROR(C23/C8,0) | D28: =IFERROR(D23/D8,0) | E28: =IFERROR(E23/E8,0) | F28: =IFERROR(F23/F8,0) | G28: =IFERROR(G23/G8,0) | H28: =IFERROR(H23/H8,0) | I28: =IFERROR(I23/I8,0) | ... R28: =IFERROR(R23/R8,0)
A29: Services Margin % | B29: =IFERROR(B24/B10,0) | C29: =IFERROR(C24/C10,0) | D29: =IFERROR(D24/D10,0) | E29: =IFERROR(E24/E10,0) | F29: =IFERROR(F24/F10,0) | G29: =IFERROR(G24/G10,0) | H29: =IFERROR(H24/H10,0) | I29: =IFERROR(I24/I10,0) | ... R29: =IFERROR(R24/R10,0)
A30: Total Margin % | B30: =IFERROR(B25/B11,0) | C30: =IFERROR(C25/C11,0) | D30: =IFERROR(D25/D11,0) | E30: =IFERROR(E25/E11,0) | F30: =IFERROR(F25/F11,0) | G30: =IFERROR(G25/G11,0) | H30: =IFERROR(H25/H11,0) | I30: =IFERROR(I25/I11,0) | ... R30: =IFERROR(R25/R11,0)
A32: R&D
A33: R&D (includes Cap Software) | B33: 443.47 | C33: 404.34 | D33: 492.87 | E33: 456.44 | F33: 433.01 | G33: 503.02 | H33: 452.84 | I33: 470.83 | J33: 455.62 | K33: 539.75 | L33: 498.33 | M33: 568.01 | N33: =SUM(B33:D33) | O33: =SUM(E33:G33) | P33: =SUM(H33:J33) | Q33: =SUM(K33:M33) | R33: =SUM(B33:M33)
A34: Research & Development | B34: 305.48 | C34: 270.22 | D34: 363.03 | E34: 329.9 | F34: 297.29 | G34: 334.7 | H34: 339.47 | I34: 318.22 | J34: 338.29 | K34: 359.77 | L34: 358.39 | M34: 374.95 | N34: =SUM(B34:D34) | O34: =SUM(E34:G34) | P34: =SUM(H34:J34) | Q34: =SUM(K34:M34) | R34: =SUM(B34:M34)
A35: Capitalized R&D | B35: -137.99 | C35: -134.12 | D35: -129.84 | E35: -126.54 | F35: -135.72 | G35: -168.32 | H35: -113.37 | I35: -152.61 | J35: -117.33 | K35: -179.98 | L35: -139.94 | M35: -193.06 | N35: =SUM(B35:D35) | O35: =SUM(E35:G35) | P35: =SUM(H35:J35) | Q35: =SUM(K35:M35) | R35: =SUM(B35:M35)
A36: Product Management | B36: 176.75 | C36: 157.99 | D36: 159.41 | E36: 173.28 | F36: 162.42 | G36: 162.7 | H36: 185.66 | I36: 185.45 | J36: 199.61 | K36: 204.26 | L36: 214.58 | M36: 189.71 | N36: =SUM(B36:D36) | O36: =SUM(E36:G36) | P36: =SUM(H36:J36) | Q36: =SUM(K36:M36) | R36: =SUM(B36:M36)
A38: Contribution Margin + R&D $ | B38: =B25-B33-B36 | C38: =C25-C33-C36 | D38: =D25-D33-D36 | E38: =E25-E33-E36 | F38: =F25-F33-F36 | G38: =G25-G33-G36 | H38: =H25-H33-H36 | I38: =I25-I33-I36 | ... M38: =M25-M33-M36 | N38: =SUM(B38:D38) | O38: =SUM(E38:G38) | P38: =SUM(H38:J38) | Q38: =SUM(K38:M38) | R38: =SUM(B38:M38)
A39: Contribution Margin + R&D % | B39: =IFERROR(B38/B11,0) | C39: =IFERROR(C38/C11,0) | D39: =IFERROR(D38/D11,0) | E39: =IFERROR(E38/E11,0) | F39: =IFERROR(F38/F11,0) | G39: =IFERROR(G38/G11,0) | H39: =IFERROR(H38/H11,0) | I39: =IFERROR(I38/I11,0) | ... R39: =IFERROR(R38/R11,0)
A42: Affirm
A43: Revenue
A44: Subscription | B44: 2046.95 | C44: 1980.7 | D44: 1979.69 | E44: 2092.06 | F44: 2122.54 | G44: 2127.6 | H44: 2159.9 | I44: 2134.14 | J44: 2105.26 | K44: 2392.87 | L44: 2379.39 | M44: 2405.21 | N44: =SUM(B44:D44) | O44: =SUM(E44:G44) | P44: =SUM(H44:J44) | Q44: =SUM(K44:M44) | R44: =SUM(B44:M44)
A45: Transactions | B45: 496.93 | C45: 457.06 | D45: 486.98 | E45: 422.43 | F45: 484.32 | G45: 529.28 | H45: 455.67 | I45: 505.22 | J45: 462.18 | K45: 540.08 | L45: 540.19 | M45: 519.53 | N45: =SUM(B45:D45) | O45: =SUM(E45:G45) | P45: =SUM(H45:J45) | Q45: =SUM(K45:M45) | R45: =SUM(B45:M45)
A46: Services | B46: 101.1 | C46: 259.71 | D46: 232.43 | E46: 208.51 | F46: 209.06 | G46: 205.67 | H46: 259.86 | I46: 179.98 | J46: 277.29 | K46: 135.78 | L46: 244.91 | M46: 342.99 | N46: =SUM(B46:D46) | O46: =SUM(E46:G46) | P46: =SUM(H46:J46) | Q46: =SUM(K46:M46) | R46: =SUM(B46:M46)
A47: Revenue | B47: =B44+B45+B46 | C47: =C44+C45+C46 | D47: =D44+D45+D46 | E47: =E44+E45+E46 | F47: =F44+F45+F46 | G47: =G44+G45+G46 | H47: =H44+H45+H46 | I47: =I44+I45+I46 | ... M47: =M44+M45+M46 | N47: =SUM(B47:D47) | O47: =SUM(E47:G47) | P47: =SUM(H47:J47) | Q47: =SUM(K47:M47) | R47: =SUM(B47:M47)
A49: Cost of Revenue
A50: NetOps | B50: 119.74 | C50: 114.12 | D50: 122.11 | E50: 130.35 | F50: 126.16 | G50: 129.2 | H50: 125.12 | I50: 133.55 | J50: 130.92 | K50: 150.41 | L50: 147.2 | M50: 149.82 | N50: =SUM(B50:D50) | O50: =SUM(E50:G50) | P50: =SUM(H50:J50) | Q50: =SUM(K50:M50) | R50: =SUM(B50:M50)
A51: Security | B51: 38.99 | C51: 40.55 | D51: 38.93 | E51: 43.64 | F51: 43.73 | G51: 44.1 | H51: 44.54 | I51: 41.69 | J51: 43.32 | K51: 45.98 | L51: 49.36 | M51: 49.83 | N51: =SUM(B51:D51) | O51: =SUM(E51:G51) | P51: =SUM(H51:J51) | Q51: =SUM(K51:M51) | R51: =SUM(B51:M51)
A52: Support | B52: 59.7 | C52: 61.3 | D52: 59.15 | E52: 61.54 | F52: 65.56 | G52: 62.09 | H52: 61.71 | I52: 62.06 | J52: 62.07 | K52: 74.4 | L52: 74.71 | M52: 70.56 | N52: =SUM(B52:D52) | O52: =SUM(E52:G52) | P52: =SUM(H52:J52) | Q52: =SUM(K52:M52) | R52: =SUM(B52:M52)
A53: Partners | B53: 41.52 | C53: 39.22 | D53: 41.5 | E53: 41.99 | F53: 44.32 | G53: 40.92 | H53: 45.23 | I53: 41.31 | J53: 44.05 | K53: 46.73 | L53: 45.72 | M53: 47.79 | N53: =SUM(B53:D53) | O53: =SUM(E53:G53) | P53: =SUM(H53:J53) | Q53: =SUM(K53:M53) | R53: =SUM(B53:M53)
A54: Content | B54: 6.28 | C54: 5.83 | D54: 6 | E54: 6.28 | F54: 6.29 | G54: 6.43 | H54: 6.32 | I54: 6.54 | J54: 6 | K54: 7.48 | L54: 7.17 | M54: 7.37 | N54: =SUM(B54:D54) | O54: =SUM(E54:G54) | P54: =SUM(H54:J54) | Q54: =SUM(K54:M54) | R54: =SUM(B54:M54)
A55: Cost of Subscription | B55: =SUM(B50:B54) | C55: =SUM(C50:C54) | D55: =SUM(D50:D54) | E55: =SUM(E50:E54) | F55: =SUM(F50:F54) | G55: =SUM(G50:G54) | H55: =SUM(H50:H54) | I55: =SUM(I50:I54) | ... M55: =SUM(M50:M54) | N55: =SUM(B55:D55) | O55: =SUM(E55:G55) | P55: =SUM(H55:J55) | Q55: =SUM(K55:M55) | R55: =SUM(B55:M55)
A56: Cost of Services | B56: 42.4 | C56: 107.3 | D56: 97.06 | E56: 81.78 | F56: 90.99 | G56: 78.99 | H56: 102.49 | I56: 71.16 | J56: 117.48 | K56: 55.76 | L56: 101.35 | M56: 130.19 | N56: =SUM(B56:D56) | O56: =SUM(E56:G56) | P56: =SUM(H56:J56) | Q56: =SUM(K56:M56) | R56: =SUM(B56:M56)
A57: Cost of Revenue | B57: =B55+B56 | C57: =C55+C56 | D57: =D55+D56 | E57: =E55+E56 | F57: =F55+F56 | G57: =G55+G56 | H57: =H55+H56 | I57: =I55+I56 | ... M57: =M55+M56 | N57: =SUM(B57:D57) | O57: =SUM(E57:G57) | P57: =SUM(H57:J57) | Q57: =SUM(K57:M57) | R57: =SUM(B57:M57)
A59: Subscriptions Contribution | B59: =B44-B55 | C59: =C44-C55 | D59: =D44-D55 | E59: =E44-E55 | F59: =F44-F55 | G59: =G44-G55 | H59: =H44-H55 | I59: =I44-I55 | ... M59: =M44-M55 | N59: =SUM(B59:D59) | O59: =SUM(E59:G59) | P59: =SUM(H59:J59) | Q59: =SUM(K59:M59) | R59: =SUM(B59:M59)
A60: Services Contribution | B60: =B46-B56 | C60: =C46-C56 | D60: =D46-D56 | E60: =E46-E56 | F60: =F46-F56 | G60: =G46-G56 | H60: =H46-H56 | I60: =I46-I56 | ... M60: =M46-M56 | N60: =SUM(B60:D60) | O60: =SUM(E60:G60) | P60: =SUM(H60:J60) | Q60: =SUM(K60:M60) | R60: =SUM(B60:M60)
A61: Contribution Margin | B61: =B59+B60 | C61: =C59+C60 | D61: =D59+D60 | E61: =E59+E60 | F61: =F59+F60 | G61: =G59+G60 | H61: =H59+H60 | I61: =I59+I60 | ... M61: =M59+M60 | N61: =SUM(B61:D61) | O61: =SUM(E61:G61) | P61: =SUM(H61:J61) | Q61: =SUM(K61:M61) | R61: =SUM(B61:M61)
A62: D&A | B62: 26.45 | C62: 26.97 | D62: 26.99 | E62: 27.23 | F62: 28.16 | G62: 28.63 | H62: 28.75 | I62: 28.19 | J62: 28.45 | K62: 30.69 | L62: 31.64 | M62: 32.68 | N62: =SUM(B62:D62) | O62: =SUM(E62:G62) | P62: =SUM(H62:J62) | Q62: =SUM(K62:M62) | R62: =SUM(B62:M62)
A63: Contribution Margin GAAP | B63: =B61-B62 | C63: =C61-C62 | D63: =D61-D62 | E63: =E61-E62 | F63: =F61-F62 | G63: =G61-G62 | H63: =H61-H62 | I63: =I61-I62 | ... M63: =M61-M62 | N63: =SUM(B63:D63) | O63: =SUM(E63:G63) | P63: =SUM(H63:J63) | Q63: =SUM(K63:M63) | R63: =SUM(B63:M63)
A64: Subscription Margin % | B64: =IFERROR(B59/B44,0) | C64: =IFERROR(C59/C44,0) | D64: =IFERROR(D59/D44,0) | E64: =IFERROR(E59/E44,0) | F64: =IFERROR(F59/F44,0) | G64: =IFERROR(G59/G44,0) | H64: =IFERROR(H59/H44,0) | I64: =IFERROR(I59/I44,0) | ... R64: =IFERROR(R59/R44,0)
A65: Services Margin % | B65: =IFERROR(B60/B46,0) | C65: =IFERROR(C60/C46,0) | D65: =IFERROR(D60/D46,0) | E65: =IFERROR(E60/E46,0) | F65: =IFERROR(F60/F46,0) | G65: =IFERROR(G60/G46,0) | H65: =IFERROR(H60/H46,0) | I65: =IFERROR(I60/I46,0) | ... R65: =IFERROR(R60/R46,0)
A66: Total Margin % | B66: =IFERROR(B61/B47,0) | C66: =IFERROR(C61/C47,0) | D66: =IFERROR(D61/D47,0) | E66: =IFERROR(E61/E47,0) | F66: =IFERROR(F61/F47,0) | G66: =IFERROR(G61/G47,0) | H66: =IFERROR(H61/H47,0) | I66: =IFERROR(I61/I47,0) | ... R66: =IFERROR(R61/R47,0)
A68: R&D
A69: R&D (includes Cap Software) | B69: 135.86 | C69: 131.21 | D69: 130.64 | E69: 131.7 | F69: 144.79 | G69: 144.23 | H69: 145.61 | I69: 134.51 | J69: 134.72 | K69: 149.39 | L69: 151.25 | M69: 162.74 | N69: =SUM(B69:D69) | O69: =SUM(E69:G69) | P69: =SUM(H69:J69) | Q69: =SUM(K69:M69) | R69: =SUM(B69:M69)
A70: Research & Development | B70: 96.95 | C70: 94.29 | D70: 93.94 | E70: 97.1 | F70: 95.52 | G70: 108.17 | H70: 99.67 | I70: 94.52 | J70: 99.9 | K70: 99.82 | L70: 110.43 | M70: 108.23 | N70: =SUM(B70:D70) | O70: =SUM(E70:G70) | P70: =SUM(H70:J70) | Q70: =SUM(K70:M70) | R70: =SUM(B70:M70)
A71: Capitalized R&D | B71: -38.91 | C71: -36.92 | D71: -36.7 | E71: -34.6 | F71: -49.27 | G71: -36.06 | H71: -45.94 | I71: -39.99 | J71: -34.82 | K71: -49.57 | L71: -40.82 | M71: -54.51 | N71: =SUM(B71:D71) | O71: =SUM(E71:G71) | P71: =SUM(H71:J71) | Q71: =SUM(K71:M71) | R71: =SUM(B71:M71)
A72: Product Management | B72: 48.35 | C72: 57.7 | D72: 52.99 | E72: 53.59 | F72: 57.62 | G72: 54.81 | H72: 57.11 | I72: 60.91 | J72: 57.07 | K72: 64.46 | L72: 57.27 | M72: 59.77 | N72: =SUM(B72:D72) | O72: =SUM(E72:G72) | P72: =SUM(H72:J72) | Q72: =SUM(K72:M72) | R72: =SUM(B72:M72)
A74: Contribution Margin + R&D $ | B74: =B61-B69-B72 | C74: =C61-C69-C72 | D74: =D61-D69-D72 | E74: =E61-E69-E72 | F74: =F61-F69-F72 | G74: =G61-G69-G72 | H74: =H61-H69-H72 | I74: =I61-I69-I72 | ... M74: =M61-M69-M72 | N74: =SUM(B74:D74) | O74: =SUM(E74:G74) | P74: =SUM(H74:J74) | Q74: =SUM(K74:M74) | R74: =SUM(B74:M74)
A75: Contribution Margin + R&D % | B75: =IFERROR(B74/B47,0) | C75: =IFERROR(C74/C47,0) | D75: =IFERROR(D74/D47,0) | E75: =IFERROR(E74/E47,0) | F75: =IFERROR(F74/F47,0) | G75: =IFERROR(G74/G47,0) | H75: =IFERROR(H74/H47,0) | I75: =IFERROR(I74/I47,0) | ... R75: =IFERROR(R74/R47,0)
A78: InsureSight
A79: Revenue
A80: Subscription | B80: 642.02 | C80: 646.87 | D80: 636.13 | E80: 670.09 | F80: 705.94 | G80: 693.17 | H80: 667.61 | I80: 720.21 | J80: 733.31 | K80: 799.16 | L80: 773.02 | M80: 788.21 | N80: =SUM(B80:D80) | O80: =SUM(E80:G80) | P80: =SUM(H80:J80) | Q80: =SUM(K80:M80) | R80: =SUM(B80:M80)
A81: Transactions | B81: 149.16 | C81: 138.54 | D81: 151.97 | E81: 168.3 | F81: 139.58 | G81: 165.15 | H81: 139.97 | I81: 160.26 | J81: 176.49 | K81: 163.5 | L81: 175.93 | M81: 177 | N81: =SUM(B81:D81) | O81: =SUM(E81:G81) | P81: =SUM(H81:J81) | Q81: =SUM(K81:M81) | R81: =SUM(B81:M81)
A82: Services | B82: 68.39 | C82: 86.96 | D82: 79.09 | E82: 65.37 | F82: 67.75 | G82: 76 | H82: 93.73 | I82: 46.71 | J82: 63.23 | K82: 74.7 | L82: 103 | M82: 84.09 | N82: =SUM(B82:D82) | O82: =SUM(E82:G82) | P82: =SUM(H82:J82) | Q82: =SUM(K82:M82) | R82: =SUM(B82:M82)
A83: Revenue | B83: =B80+B81+B82 | C83: =C80+C81+C82 | D83: =D80+D81+D82 | E83: =E80+E81+E82 | F83: =F80+F81+F82 | G83: =G80+G81+G82 | H83: =H80+H81+H82 | I83: =I80+I81+I82 | ... M83: =M80+M81+M82 | N83: =SUM(B83:D83) | O83: =SUM(E83:G83) | P83: =SUM(H83:J83) | Q83: =SUM(K83:M83) | R83: =SUM(B83:M83)
A85: Cost of Revenue
A86: NetOps | B86: 140.04 | C86: 144.16 | D86: 135.67 | E86: 150.31 | F86: 155.22 | G86: 148.59 | H86: 149.17 | I86: 150.61 | J86: 165.38 | K86: 180.56 | L86: 163.37 | M86: 172.11 | N86: =SUM(B86:D86) | O86: =SUM(E86:G86) | P86: =SUM(H86:J86) | Q86: =SUM(K86:M86) | R86: =SUM(B86:M86)
A87: Security | B87: 31.06 | C87: 33.82 | D87: 31.86 | E87: 32 | F87: 34.41 | G87: 35.87 | H87: 33.24 | I87: 37.1 | J87: 37.28 | K87: 41.91 | L87: 39.02 | M87: 41.18 | N87: =SUM(B87:D87) | O87: =SUM(E87:G87) | P87: =SUM(H87:J87) | Q87: =SUM(K87:M87) | R87: =SUM(B87:M87)
A88: Support | B88: 53.37 | C88: 52.33 | D88: 52.01 | E88: 53.63 | F88: 58.34 | G88: 55.72 | H88: 55.53 | I88: 59.02 | J88: 58.52 | K88: 62.39 | L88: 60.28 | M88: 63.92 | N88: =SUM(B88:D88) | O88: =SUM(E88:G88) | P88: =SUM(H88:J88) | Q88: =SUM(K88:M88) | R88: =SUM(B88:M88)
A89: Partners | B89: 39.55 | C89: 38.89 | D89: 38.65 | E89: 39.3 | F89: 40.57 | G89: 40.7 | H89: 39.14 | I89: 42.43 | J89: 44.18 | K89: 46.22 | L89: 45.13 | M89: 48.21 | N89: =SUM(B89:D89) | O89: =SUM(E89:G89) | P89: =SUM(H89:J89) | Q89: =SUM(K89:M89) | R89: =SUM(B89:M89)
A90: Content | B90: 6.55 | C90: 6.19 | D90: 6.3 | E90: 6.73 | F90: 7 | G90: 6.73 | H90: 6.62 | I90: 7.49 | J90: 7.39 | K90: 8.15 | L90: 8.01 | M90: 8.09 | N90: =SUM(B90:D90) | O90: =SUM(E90:G90) | P90: =SUM(H90:J90) | Q90: =SUM(K90:M90) | R90: =SUM(B90:M90)
A91: Cost of Subscription | B91: =SUM(B86:B90) | C91: =SUM(C86:C90) | D91: =SUM(D86:D90) | E91: =SUM(E86:E90) | F91: =SUM(F86:F90) | G91: =SUM(G86:G90) | H91: =SUM(H86:H90) | I91: =SUM(I86:I90) | ... M91: =SUM(M86:M90) | N91: =SUM(B91:D91) | O91: =SUM(E91:G91) | P91: =SUM(H91:J91) | Q91: =SUM(K91:M91) | R91: =SUM(B91:M91)
A92: Cost of Services | B92: 43.39 | C92: 60.52 | D92: 51.88 | E92: 41.95 | F92: 43.19 | G92: 50.61 | H92: 55.16 | I92: 27.63 | J92: 43.25 | K92: 46.15 | L92: 73.64 | M92: 56.32 | N92: =SUM(B92:D92) | O92: =SUM(E92:G92) | P92: =SUM(H92:J92) | Q92: =SUM(K92:M92) | R92: =SUM(B92:M92)
A93: Cost of Revenue | B93: =B91+B92 | C93: =C91+C92 | D93: =D91+D92 | E93: =E91+E92 | F93: =F91+F92 | G93: =G91+G92 | H93: =H91+H92 | I93: =I91+I92 | ... M93: =M91+M92 | N93: =SUM(B93:D93) | O93: =SUM(E93:G93) | P93: =SUM(H93:J93) | Q93: =SUM(K93:M93) | R93: =SUM(B93:M93)
A95: Subscriptions Contribution | B95: =B80-B91 | C95: =C80-C91 | D95: =D80-D91 | E95: =E80-E91 | F95: =F80-F91 | G95: =G80-G91 | H95: =H80-H91 | I95: =I80-I91 | ... M95: =M80-M91 | N95: =SUM(B95:D95) | O95: =SUM(E95:G95) | P95: =SUM(H95:J95) | Q95: =SUM(K95:M95) | R95: =SUM(B95:M95)
A96: Services Contribution | B96: =B82-B92 | C96: =C82-C92 | D96: =D82-D92 | E96: =E82-E92 | F96: =F82-F92 | G96: =G82-G92 | H96: =H82-H92 | I96: =I82-I92 | ... M96: =M82-M92 | N96: =SUM(B96:D96) | O96: =SUM(E96:G96) | P96: =SUM(H96:J96) | Q96: =SUM(K96:M96) | R96: =SUM(B96:M96)
A97: Contribution Margin | B97: =B95+B96 | C97: =C95+C96 | D97: =D95+D96 | E97: =E95+E96 | F97: =F95+F96 | G97: =G95+G96 | H97: =H95+H96 | I97: =I95+I96 | ... M97: =M95+M96 | N97: =SUM(B97:D97) | O97: =SUM(E97:G97) | P97: =SUM(H97:J97) | Q97: =SUM(K97:M97) | R97: =SUM(B97:M97)
A98: D&A | B98: 8.6 | C98: 8.72 | D98: 8.67 | E98: 9.04 | F98: 9.13 | G98: 9.34 | H98: 9.01 | I98: 9.27 | J98: 9.73 | K98: 10.37 | L98: 10.52 | M98: 10.49 | N98: =SUM(B98:D98) | O98: =SUM(E98:G98) | P98: =SUM(H98:J98) | Q98: =SUM(K98:M98) | R98: =SUM(B98:M98)
A99: Contribution Margin GAAP | B99: =B97-B98 | C99: =C97-C98 | D99: =D97-D98 | E99: =E97-E98 | F99: =F97-F98 | G99: =G97-G98 | H99: =H97-H98 | I99: =I97-I98 | ... M99: =M97-M98 | N99: =SUM(B99:D99) | O99: =SUM(E99:G99) | P99: =SUM(H99:J99) | Q99: =SUM(K99:M99) | R99: =SUM(B99:M99)
A100: Subscription Margin % | B100: =IFERROR(B95/B80,0) | C100: =IFERROR(C95/C80,0) | D100: =IFERROR(D95/D80,0) | E100: =IFERROR(E95/E80,0) | F100: =IFERROR(F95/F80,0) | G100: =IFERROR(G95/G80,0) | H100: =IFERROR(H95/H80,0) | I100: =IFERROR(I95/I80,0) | ... R100: =IFERROR(R95/R80,0)
A101: Services Margin % | B101: =IFERROR(B96/B82,0) | C101: =IFERROR(C96/C82,0) | D101: =IFERROR(D96/D82,0) | E101: =IFERROR(E96/E82,0) | F101: =IFERROR(F96/F82,0) | G101: =IFERROR(G96/G82,0) | H101: =IFERROR(H96/H82,0) | I101: =IFERROR(I96/I82,0) | ... R101: =IFERROR(R96/R82,0)
A102: Total Margin % | B102: =IFERROR(B97/B83,0) | C102: =IFERROR(C97/C83,0) | D102: =IFERROR(D97/D83,0) | E102: =IFERROR(E97/E83,0) | F102: =IFERROR(F97/F83,0) | G102: =IFERROR(G97/G83,0) | H102: =IFERROR(H97/H83,0) | I102: =IFERROR(I97/I83,0) | ... R102: =IFERROR(R97/R83,0)
A104: R&D
A105: R&D (includes Cap Software) | B105: 94.99 | C105: 112.28 | D105: 105.78 | E105: 100.28 | F105: 103.72 | G105: 103.63 | H105: 110.63 | I105: 109.11 | J105: 114.51 | K105: 116.16 | L105: 123.2 | M105: 131.04 | N105: =SUM(B105:D105) | O105: =SUM(E105:G105) | P105: =SUM(H105:J105) | Q105: =SUM(K105:M105) | R105: =SUM(B105:M105)
A106: Research & Development | B106: 67.9 | C106: 79.51 | D106: 77 | E106: 71.84 | F106: 72.94 | G106: 73.64 | H106: 81.47 | I106: 79.52 | J106: 77.27 | K106: 86.89 | L106: 84.39 | M106: 85.84 | N106: =SUM(B106:D106) | O106: =SUM(E106:G106) | P106: =SUM(H106:J106) | Q106: =SUM(K106:M106) | R106: =SUM(B106:M106)
A107: Capitalized R&D | B107: -27.09 | C107: -32.77 | D107: -28.78 | E107: -28.44 | F107: -30.78 | G107: -29.99 | H107: -29.16 | I107: -29.59 | J107: -37.24 | K107: -29.27 | L107: -38.81 | M107: -45.2 | N107: =SUM(B107:D107) | O107: =SUM(E107:G107) | P107: =SUM(H107:J107) | Q107: =SUM(K107:M107) | R107: =SUM(B107:M107)
A108: Product Management | B108: 36.13 | C108: 36.62 | D108: 32.74 | E108: 37.45 | F108: 33.81 | G108: 37.85 | H108: 35.78 | I108: 35.8 | J108: 41.5 | K108: 41.82 | L108: 44.44 | M108: 39.45 | N108: =SUM(B108:D108) | O108: =SUM(E108:G108) | P108: =SUM(H108:J108) | Q108: =SUM(K108:M108) | R108: =SUM(B108:M108)
A110: Contribution Margin + R&D $ | B110: =B97-B105-B108 | C110: =C97-C105-C108 | D110: =D97-D105-D108 | E110: =E97-E105-E108 | F110: =F97-F105-F108 | G110: =G97-G105-G108 | H110: =H97-H105-H108 | I110: =I97-I105-I108 | ... M110: =M97-M105-M108 | N110: =SUM(B110:D110) | O110: =SUM(E110:G110) | P110: =SUM(H110:J110) | Q110: =SUM(K110:M110) | R110: =SUM(B110:M110)
A111: Contribution Margin + R&D % | B111: =IFERROR(B110/B83,0) | C111: =IFERROR(C110/C83,0) | D111: =IFERROR(D110/D83,0) | E111: =IFERROR(E110/E83,0) | F111: =IFERROR(F110/F83,0) | G111: =IFERROR(G110/G83,0) | H111: =IFERROR(H110/H83,0) | I111: =IFERROR(I110/I83,0) | ... R111: =IFERROR(R110/R83,0)
A114: DocFast
A115: Revenue
A116: Subscription | B116: 269.34 | C116: 277.48 | D116: 277.81 | E116: 276.83 | F116: 267.19 | G116: 288.37 | H116: 276.8 | I116: 298.92 | J116: 305.22 | K116: 331.32 | L116: 331.74 | M116: 332.02 | N116: =SUM(B116:D116) | O116: =SUM(E116:G116) | P116: =SUM(H116:J116) | Q116: =SUM(K116:M116) | R116: =SUM(B116:M116)
A117: Transactions | B117: 62.18 | C117: 54.82 | D117: 60.58 | E117: 57.27 | F117: 60.68 | G117: 61.87 | H117: 69.69 | I117: 73.31 | J117: 61.25 | K117: 77.92 | L117: 79.72 | M117: 67.33 | N117: =SUM(B117:D117) | O117: =SUM(E117:G117) | P117: =SUM(H117:J117) | Q117: =SUM(K117:M117) | R117: =SUM(B117:M117)
A118: Services | B118: 19.89 | C118: 23.81 | D118: 31.96 | E118: 23.98 | F118: 33.44 | G118: 33.7 | H118: 26.31 | I118: 25.19 | J118: 36.45 | K118: 15.55 | L118: 14.7 | M118: 30.48 | N118: =SUM(B118:D118) | O118: =SUM(E118:G118) | P118: =SUM(H118:J118) | Q118: =SUM(K118:M118) | R118: =SUM(B118:M118)
A119: Revenue | B119: =B116+B117+B118 | C119: =C116+C117+C118 | D119: =D116+D117+D118 | E119: =E116+E117+E118 | F119: =F116+F117+F118 | G119: =G116+G117+G118 | H119: =H116+H117+H118 | I119: =I116+I117+I118 | ... M119: =M116+M117+M118 | N119: =SUM(B119:D119) | O119: =SUM(E119:G119) | P119: =SUM(H119:J119) | Q119: =SUM(K119:M119) | R119: =SUM(B119:M119)
A121: Cost of Revenue
...

Sheet Functional P&L Summary - Jan 25
A1: Keystone BenefitTech, Inc. | E1: Last Updated: 2026-02-28
A2: Functional P&L Summary — January 2025
A4: Line Item | B4: iGO | C4: Affirm | D4: InsureSight | E4: US
A5: Revenue
A6: Subscription | B6: ='Functional P&L - Monthly Trend'!B8 | C6: ='Functional P&L - Monthly Trend'!B44 | D6: ='Functional P&L - Monthly Trend'!B80 | E6: =SUM(B6:D6)
A7: Transactions | B7: ='Functional P&L - Monthly Trend'!B9 | C7: ='Functional P&L - Monthly Trend'!B45 | D7: ='Functional P&L - Monthly Trend'!B81 | E7: =SUM(B7:D7)
A8: Services | B8: ='Functional P&L - Monthly Trend'!B10 | C8: ='Functional P&L - Monthly Trend'!B46 | D8: ='Functional P&L - Monthly Trend'!B82 | E8: =SUM(B8:D8)
A9: Revenue | B9: ='Functional P&L - Monthly Trend'!B11 | C9: ='Functional P&L - Monthly Trend'!B47 | D9: ='Functional P&L - Monthly Trend'!B83 | E9: =SUM(B9:D9)
A11: Cost of Revenue
A12: NetOps | B12: ='Functional P&L - Monthly Trend'!B14 | C12: ='Functional P&L - Monthly Trend'!B50 | D12: ='Functional P&L - Monthly Trend'!B86 | E12: =SUM(B12:D12)
A13: Security | B13: ='Functional P&L - Monthly Trend'!B15 | C13: ='Functional P&L - Monthly Trend'!B51 | D13: ='Functional P&L - Monthly Trend'!B87 | E13: =SUM(B13:D13)
A14: Support | B14: ='Functional P&L - Monthly Trend'!B16 | C14: ='Functional P&L - Monthly Trend'!B52 | D14: ='Functional P&L - Monthly Trend'!B88 | E14: =SUM(B14:D14)
A15: Partners | B15: ='Functional P&L - Monthly Trend'!B17 | C15: ='Functional P&L - Monthly Trend'!B53 | D15: ='Functional P&L - Monthly Trend'!B89 | E15: =SUM(B15:D15)
A16: Content | B16: ='Functional P&L - Monthly Trend'!B18 | C16: ='Functional P&L - Monthly Trend'!B54 | D16: ='Functional P&L - Monthly Trend'!B90 | E16: =SUM(B16:D16)
A17: Cost of Subscription | B17: ='Functional P&L - Monthly Trend'!B19 | C17: ='Functional P&L - Monthly Trend'!B55 | D17: ='Functional P&L - Monthly Trend'!B91 | E17: =SUM(B17:D17)
A18: Cost of Services | B18: ='Functional P&L - Monthly Trend'!B20 | C18: ='Functional P&L - Monthly Trend'!B56 | D18: ='Functional P&L - Monthly Trend'!B92 | E18: =SUM(B18:D18)
A19: Cost of Revenue | B19: ='Functional P&L - Monthly Trend'!B21 | C19: ='Functional P&L - Monthly Trend'!B57 | D19: ='Functional P&L - Monthly Trend'!B93 | E19: =SUM(B19:D19)
A21: Subscriptions Contribution | B21: ='Functional P&L - Monthly Trend'!B23 | C21: ='Functional P&L - Monthly Trend'!B59 | D21: ='Functional P&L - Monthly Trend'!B95 | E21: =SUM(B21:D21)
A22: Services Contribution | B22: ='Functional P&L - Monthly Trend'!B24 | C22: ='Functional P&L - Monthly Trend'!B60 | D22: ='Functional P&L - Monthly Trend'!B96 | E22: =SUM(B22:D22)
A23: Contribution Margin | B23: ='Functional P&L - Monthly Trend'!B25 | C23: ='Functional P&L - Monthly Trend'!B61 | D23: ='Functional P&L - Monthly Trend'!B97 | E23: =SUM(B23:D23)
A24: D&A | B24: ='Functional P&L - Monthly Trend'!B26 | C24: ='Functional P&L - Monthly Trend'!B62 | D24: ='Functional P&L - Monthly Trend'!B98 | E24: =SUM(B24:D24)
A25: Contribution Margin GAAP | B25: ='Functional P&L - Monthly Trend'!B27 | C25: ='Functional P&L - Monthly Trend'!B63 | D25: ='Functional P&L - Monthly Trend'!B99 | E25: =SUM(B25:D25)
A26: Subscription Margin % | B26: ='Functional P&L - Monthly Trend'!B28 | C26: ='Functional P&L - Monthly Trend'!B64 | D26: ='Functional P&L - Monthly Trend'!B100 | E26: =IFERROR(E21/E6,0)
A27: Services Margin % | B27: ='Functional P&L - Monthly Trend'!B29 | C27: ='Functional P&L - Monthly Trend'!B65 | D27: ='Functional P&L - Monthly Trend'!B101 | E27: =IFERROR(E22/E8,0)
A28: Total Margin % | B28: ='Functional P&L - Monthly Trend'!B30 | C28: ='Functional P&L - Monthly Trend'!B66 | D28: ='Functional P&L - Monthly Trend'!B102 | E28: =IFERROR(E23/E9,0)
A30: R&D
A31: R&D (includes Cap Software) | B31: ='Functional P&L - Monthly Trend'!B33 | C31: ='Functional P&L - Monthly Trend'!B69 | D31: ='Functional P&L - Monthly Trend'!B105 | E31: =SUM(B31:D31)
A32: Research & Development | B32: ='Functional P&L - Monthly Trend'!B34 | C32: ='Functional P&L - Monthly Trend'!B70 | D32: ='Functional P&L - Monthly Trend'!B106 | E32: =SUM(B32:D32)
A33: Capitalized R&D | B33: ='Functional P&L - Monthly Trend'!B35 | C33: ='Functional P&L - Monthly Trend'!B71 | D33: ='Functional P&L - Monthly Trend'!B107 | E33: =SUM(B33:D33)
A34: Product Management | B34: ='Functional P&L - Monthly Trend'!B36 | C34: ='Functional P&L - Monthly Trend'!B72 | D34: ='Functional P&L - Monthly Trend'!B108 | E34: =SUM(B34:D34)
A36: Contribution Margin + R&D $ | B36: ='Functional P&L - Monthly Trend'!B38 | C36: ='Functional P&L - Monthly Trend'!B74 | D36: ='Functional P&L - Monthly Trend'!B110 | E36: =SUM(B36:D36)
A37: Contribution Margin + R&D % | B37: ='Functional P&L - Monthly Trend'!B39 | C37: ='Functional P&L - Monthly Trend'!B75 | D37: ='Functional P&L - Monthly Trend'!B111 | E37: =IFERROR(E36/E9,0)

Sheet Functional P&L Summary - Feb 25
A1: Keystone BenefitTech, Inc. | E1: Last Updated: 2026-02-28
A2: Functional P&L Summary — February 2025
A4: Line Item | B4: iGO | C4: Affirm | D4: InsureSight | E4: US
A5: Revenue
A6: Subscription | B6: ='Functional P&L - Monthly Trend'!C8 | C6: ='Functional P&L - Monthly Trend'!C44 | D6: ='Functional P&L - Monthly Trend'!C80 | E6: =SUM(B6:D6)
A7: Transactions | B7: ='Functional P&L - Monthly Trend'!C9 | C7: ='Functional P&L - Monthly Trend'!C45 | D7: ='Functional P&L - Monthly Trend'!C81 | E7: =SUM(B7:D7)
A8: Services | B8: ='Functional P&L - Monthly Trend'!C10 | C8: ='Functional P&L - Monthly Trend'!C46 | D8: ='Functional P&L - Monthly Trend'!C82 | E8: =SUM(B8:D8)
A9: Revenue | B9: ='Functional P&L - Monthly Trend'!C11 | C9: ='Functional P&L - Monthly Trend'!C47 | D9: ='Functional P&L - Monthly Trend'!C83 | E9: =SUM(B9:D9)
A11: Cost of Revenue
A12: NetOps | B12: ='Functional P&L - Monthly Trend'!C14 | C12: ='Functional P&L - Monthly Trend'!C50 | D12: ='Functional P&L - Monthly Trend'!C86 | E12: =SUM(B12:D12)
A13: Security | B13: ='Functional P&L - Monthly Trend'!C15 | C13: ='Functional P&L - Monthly Trend'!C51 | D13: ='Functional P&L - Monthly Trend'!C87 | E13: =SUM(B13:D13)
A14: Support | B14: ='Functional P&L - Monthly Trend'!C16 | C14: ='Functional P&L - Monthly Trend'!C52 | D14: ='Functional P&L - Monthly Trend'!C88 | E14: =SUM(B14:D14)
A15: Partners | B15: ='Functional P&L - Monthly Trend'!C17 | C15: ='Functional P&L - Monthly Trend'!C53 | D15: ='Functional P&L - Monthly Trend'!C89 | E15: =SUM(B15:D15)
A16: Content | B16: ='Functional P&L - Monthly Trend'!C18 | C16: ='Functional P&L - Monthly Trend'!C54 | D16: ='Functional P&L - Monthly Trend'!C90 | E16: =SUM(B16:D16)
A17: Cost of Subscription | B17: ='Functional P&L - Monthly Trend'!C19 | C17: ='Functional P&L - Monthly Trend'!C55 | D17: ='Functional P&L - Monthly Trend'!C91 | E17: =SUM(B17:D17)
A18: Cost of Services | B18: ='Functional P&L - Monthly Trend'!C20 | C18: ='Functional P&L - Monthly Trend'!C56 | D18: ='Functional P&L - Monthly Trend'!C92 | E18: =SUM(B18:D18)
A19: Cost of Revenue | B19: ='Functional P&L - Monthly Trend'!C21 | C19: ='Functional P&L - Monthly Trend'!C57 | D19: ='Functional P&L - Monthly Trend'!C93 | E19: =SUM(B19:D19)
A21: Subscriptions Contribution | B21: ='Functional P&L - Monthly Trend'!C23 | C21: ='Functional P&L - Monthly Trend'!C59 | D21: ='Functional P&L - Monthly Trend'!C95 | E21: =SUM(B21:D21)
A22: Services Contribution | B22: ='Functional P&L - Monthly Trend'!C24 | C22: ='Functional P&L - Monthly Trend'!C60 | D22: ='Functional P&L - Monthly Trend'!C96 | E22: =SUM(B22:D22)
A23: Contribution Margin | B23: ='Functional P&L - Monthly Trend'!C25 | C23: ='Functional P&L - Monthly Trend'!C61 | D23: ='Functional P&L - Monthly Trend'!C97 | E23: =SUM(B23:D23)
A24: D&A | B24: ='Functional P&L - Monthly Trend'!C26 | C24: ='Functional P&L - Monthly Trend'!C62 | D24: ='Functional P&L - Monthly Trend'!C98 | E24: =SUM(B24:D24)
A25: Contribution Margin GAAP | B25: ='Functional P&L - Monthly Trend'!C27 | C25: ='Functional P&L - Monthly Trend'!C63 | D25: ='Functional P&L - Monthly Trend'!C99 | E25: =SUM(B25:D25)
A26: Subscription Margin % | B26: ='Functional P&L - Monthly Trend'!C28 | C26: ='Functional P&L - Monthly Trend'!C64 | D26: ='Functional P&L - Monthly Trend'!C100 | E26: =IFERROR(E21/E6,0)
A27: Services Margin % | B27: ='Functional P&L - Monthly Trend'!C29 | C27: ='Functional P&L - Monthly Trend'!C65 | D27: ='Functional P&L - Monthly Trend'!C101 | E27: =IFERROR(E22/E8,0)
A28: Total Margin % | B28: ='Functional P&L - Monthly Trend'!C30 | C28: ='Functional P&L - Monthly Trend'!C66 | D28: ='Functional P&L - Monthly Trend'!C102 | E28: =IFERROR(E23/E9,0)
A30: R&D
A31: R&D (includes Cap Software) | B31: ='Functional P&L - Monthly Trend'!C33 | C31: ='Functional P&L - Monthly Trend'!C69 | D31: ='Functional P&L - Monthly Trend'!C105 | E31: =SUM(B31:D31)
A32: Research & Development | B32: ='Functional P&L - Monthly Trend'!C34 | C32: ='Functional P&L - Monthly Trend'!C70 | D32: ='Functional P&L - Monthly Trend'!C106 | E32: =SUM(B32:D32)
A33: Capitalized R&D | B33: ='Functional P&L - Monthly Trend'!C35 | C33: ='Functional P&L - Monthly Trend'!C71 | D33: ='Functional P&L - Monthly Trend'!C107 | E33: =SUM(B33:D33)
A34: Product Management | B34: ='Functional P&L - Monthly Trend'!C36 | C34: ='Functional P&L - Monthly Trend'!C72 | D34: ='Functional P&L - Monthly Trend'!C108 | E34: =SUM(B34:D34)
A36: Contribution Margin + R&D $ | B36: ='Functional P&L - Monthly Trend'!C38 | C36: ='Functional P&L - Monthly Trend'!C74 | D36: ='Functional P&L - Monthly Trend'!C110 | E36: =SUM(B36:D36)
A37: Contribution Margin + R&D % | B37: ='Functional P&L - Monthly Trend'!C39 | C37: ='Functional P&L - Monthly Trend'!C75 | D37: ='Functional P&L - Monthly Trend'!C111 | E37: =IFERROR(E36/E9,0)

Sheet Functional P&L Summary - Mar 25
A1: Keystone BenefitTech, Inc. | E1: Last Updated: 2026-02-28
A2: Functional P&L Summary — March 2025
A4: Line Item | B4: iGO | C4: Affirm | D4: InsureSight | E4: US
A5: Revenue
A6: Subscription | B6: ='Functional P&L - Monthly Trend'!D8 | C6: ='Functional P&L - Monthly Trend'!D44 | D6: ='Functional P&L - Monthly Trend'!D80 | E6: =SUM(B6:D6)
A7: Transactions | B7: ='Functional P&L - Monthly Trend'!D9 | C7: ='Functional P&L - Monthly Trend'!D45 | D7: ='Functional P&L - Monthly Trend'!D81 | E7: =SUM(B7:D7)
A8: Services | B8: ='Functional P&L - Monthly Trend'!D10 | C8: ='Functional P&L - Monthly Trend'!D46 | D8: ='Functional P&L - Monthly Trend'!D82 | E8: =SUM(B8:D8)
A9: Revenue | B9: ='Functional P&L - Monthly Trend'!D11 | C9: ='Functional P&L - Monthly Trend'!D47 | D9: ='Functional P&L - Monthly Trend'!D83 | E9: =SUM(B9:D9)
A11: Cost of Revenue
A12: NetOps | B12: ='Functional P&L - Monthly Trend'!D14 | C12: ='Functional P&L - Monthly Trend'!D50 | D12: ='Functional P&L - Monthly Trend'!D86 | E12: =SUM(B12:D12)
A13: Security | B13: ='Functional P&L - Monthly Trend'!D15 | C13: ='Functional P&L - Monthly Trend'!D51 | D13: ='Functional P&L - Monthly Trend'!D87 | E13: =SUM(B13:D13)
A14: Support | B14: ='Functional P&L - Monthly Trend'!D16 | C14: ='Functional P&L - Monthly Trend'!D52 | D14: ='Functional P&L - Monthly Trend'!D88 | E14: =SUM(B14:D14)
A15: Partners | B15: ='Functional P&L - Monthly Trend'!D17 | C15: ='Functional P&L - Monthly Trend'!D53 | D15: ='Functional P&L - Monthly Trend'!D89 | E15: =SUM(B15:D15)
A16: Content | B16: ='Functional P&L - Monthly Trend'!D18 | C16: ='Functional P&L - Monthly Trend'!D54 | D16: ='Functional P&L - Monthly Trend'!D90 | E16: =SUM(B16:D16)
A17: Cost of Subscription | B17: ='Functional P&L - Monthly Trend'!D19 | C17: ='Functional P&L - Monthly Trend'!D55 | D17: ='Functional P&L - Monthly Trend'!D91 | E17: =SUM(B17:D17)
A18: Cost of Services | B18: ='Functional P&L - Monthly Trend'!D20 | C18: ='Functional P&L - Monthly Trend'!D56 | D18: ='Functional P&L - Monthly Trend'!D92 | E18: =SUM(B18:D18)
A19: Cost of Revenue | B19: ='Functional P&L - Monthly Trend'!D21 | C19: ='Functional P&L - Monthly Trend'!D57 | D19: ='Functional P&L - Monthly Trend'!D93 | E19: =SUM(B19:D19)
A21: Subscriptions Contribution | B21: ='Functional P&L - Monthly Trend'!D23 | C21: ='Functional P&L - Monthly Trend'!D59 | D21: ='Functional P&L - Monthly Trend'!D95 | E21: =SUM(B21:D21)
A22: Services Contribution | B22: ='Functional P&L - Monthly Trend'!D24 | C22: ='Functional P&L - Monthly Trend'!D60 | D22: ='Functional P&L - Monthly Trend'!D96 | E22: =SUM(B22:D22)
A23: Contribution Margin | B23: ='Functional P&L - Monthly Trend'!D25 | C23: ='Functional P&L - Monthly Trend'!D61 | D23: ='Functional P&L - Monthly Trend'!D97 | E23: =SUM(B23:D23)
A24: D&A | B24: ='Functional P&L - Monthly Trend'!D26 | C24: ='Functional P&L - Monthly Trend'!D62 | D24: ='Functional P&L - Monthly Trend'!D98 | E24: =SUM(B24:D24)
A25: Contribution Margin GAAP | B25: ='Functional P&L - Monthly Trend'!D27 | C25: ='Functional P&L - Monthly Trend'!D63 | D25: ='Functional P&L - Monthly Trend'!D99 | E25: =SUM(B25:D25)
A26: Subscription Margin % | B26: ='Functional P&L - Monthly Trend'!D28 | C26: ='Functional P&L - Monthly Trend'!D64 | D26: ='Functional P&L - Monthly Trend'!D100 | E26: =IFERROR(E21/E6,0)
A27: Services Margin % | B27: ='Functional P&L - Monthly Trend'!D29 | C27: ='Functional P&L - Monthly Trend'!D65 | D27: ='Functional P&L - Monthly Trend'!D101 | E27: =IFERROR(E22/E8,0)
A28: Total Margin % | B28: ='Functional P&L - Monthly Trend'!D30 | C28: ='Functional P&L - Monthly Trend'!D66 | D28: ='Functional P&L - Monthly Trend'!D102 | E28: =IFERROR(E23/E9,0)
A30: R&D
A31: R&D (includes Cap Software) | B31: ='Functional P&L - Monthly Trend'!D33 | C31: ='Functional P&L - Monthly Trend'!D69 | D31: ='Functional P&L - Monthly Trend'!D105 | E31: =SUM(B31:D31)
A32: Research & Development | B32: ='Functional P&L - Monthly Trend'!D34 | C32: ='Functional P&L - Monthly Trend'!D70 | D32: ='Functional P&L - Monthly Trend'!D106 | E32: =SUM(B32:D32)
A33: Capitalized R&D | B33: ='Functional P&L - Monthly Trend'!D35 | C33: ='Functional P&L - Monthly Trend'!D71 | D33: ='Functional P&L - Monthly Trend'!D107 | E33: =SUM(B33:D33)
A34: Product Management | B34: ='Functional P&L - Monthly Trend'!D36 | C34: ='Functional P&L - Monthly Trend'!D72 | D34: ='Functional P&L - Monthly Trend'!D108 | E34: =SUM(B34:D34)
A36: Contribution Margin + R&D $ | B36: ='Functional P&L - Monthly Trend'!D38 | C36: ='Functional P&L - Monthly Trend'!D74 | D36: ='Functional P&L - Monthly Trend'!D110 | E36: =SUM(B36:D36)
A37: Contribution Margin + R&D % | B37: ='Functional P&L - Monthly Trend'!D39 | C37: ='Functional P&L - Monthly Trend'!D75 | D37: ='Functional P&L - Monthly Trend'!D111 | E37: =IFERROR(E36/E9,0)

Sheet US January 2025 Natural P&L
A1: Keystone BenefitTech, Inc. | E1: Last Updated: 2026-02-28
A2: US January 2025 Natural P&L
A4: Line Item | B4: iGO | C4: Affirm | D4: InsureSight | E4: Total
A6: Revenue
A7: Subscriptions | B7: 5050.9 | C7: 2543.88 | D7: 791.18 | E7: =SUM(B7:D7)
A8: Services | B8: 317.61 | C8: 101.1 | D8: 68.39 | E8: =SUM(B8:D8)
A9: Revenue | B9: =SUM(B7:B8) | C9: =SUM(C7:C8) | D9: =SUM(D7:D8) | E9: =SUM(E7:E8)
A11: NetOps
A12: Employee Expenses | B12: 216.82 | C12: 33.47 | D12: 43.79 | E12: =SUM(B12:D12)
A13: Professional Fees and Outsourcing Expenses | B13: 38.92 | C13: 5.94 | D13: 7.48 | E13: =SUM(B13:D13)
A14: Software and Maintenance Expense | B14: 59.48 | C14: 9.26 | D14: 10.38 | E14: =SUM(B14:D14)
A15: AWS | B15: 233.24 | C15: 33.62 | D15: 42.23 | E15: ='AWS Allocation'!F31
A16: Connectivity Charges | B16: 70.58 | C16: 11.38 | D16: 13.87 | E16: =SUM(B16:D16)
A17: Data Center Fees | B17: 87.86 | C17: 14.37 | D17: 16.49 | E17: =SUM(B17:D17)
A18: Office Expenses & Rent Allocation | B18: 21.09 | C18: 3.62 | D18: 3.89 | E18: =SUM(B18:D18)
A19: Overhead Allocation & Chargebacks | B19: 20.17 | C19: 3.72 | D19: 4.3 | E19: =SUM(B19:D19)
A20: Other | B20: -21.86 | C20: 4.36 | D20: -2.39 | E20: =SUM(B20:D20)
A21: Total NetOps | B21: =SUM(B12:B20) | C21: =SUM(C12:C20) | D21: =SUM(D12:D20) | E21: =SUM(E12:E20)
A23: Security
A24: Employee Expenses | B24: 71.67 | C24: 16.62 | D24: 14.9 | E24: =SUM(B24:D24)
A25: Professional Fees and Outsourcing Expenses | B25: 20.76 | C25: 4.74 | D25: 3.55 | E25: =SUM(B25:D25)
A26: Software and Maintenance Expense | B26: 41.1 | C26: 9.99 | D26: 7.2 | E26: =SUM(B26:D26)
A27: Office Expenses & Rent Allocation | B27: 12.7 | C27: 3.2 | D27: 2.41 | E27: =SUM(B27:D27)
A28: Overhead Allocation & Chargebacks | B28: 11.83 | C28: 2.74 | D28: 2.17 | E28: =SUM(B28:D28)
A29: Other | B29: 4.47 | C29: 0.85 | D29: -0.36 | E29: =SUM(B29:D29)
A30: Total Security | B30: =SUM(B24:B29) | C30: =SUM(C24:C29) | D30: =SUM(D24:D29) | E30: =SUM(E24:E29)
A32: Support
A33: Employee Expenses | B33: 129.53 | C33: 34.53 | D33: 31.16 | E33: =SUM(B33:D33)
A34: Professional Fees and Outsourcing Expenses | B34: 37.42 | C34: 8.67 | D34: 7.95 | E34: =SUM(B34:D34)
A35: Software and Maintenance Expense | B35: 22.12 | C35: 6.4 | D35: 5.64 | E35: =SUM(B35:D35)
A36: Office Expenses & Rent Allocation | B36: 18.43 | C36: 4.9 | D36: 4.09 | E36: =SUM(B36:D36)
A37: Overhead Allocation & Chargebacks | B37: 17.88 | C37: 4.4 | D37: 4.05 | E37: =SUM(B37:D37)
A38: Other | B38: 8.76 | C38: 4 | D38: 1.03 | E38: =SUM(B38:D38)
A39: Total Support | B39: =SUM(B33:B38) | C39: =SUM(C33:C38) | D39: =SUM(D33:D38) | E39: =SUM(E33:E38)
A41: Partners
A42: Employee Expenses | B42: 30.08 | C42: 10.31 | D42: 9.87 | E42: =SUM(B42:D42)
A43: Professional Fees and Outsourcing Expenses | B43: 24.23 | C43: 7.77 | D43: 7.55 | E43: =SUM(B43:D43)
A44: Software and Maintenance Expense | B44: 11.88 | C44: 4.37 | D44: 4.01 | E44: =SUM(B44:D44)
A45: Reselling Expenses | B45: 35.23 | C45: 12.66 | D45: 11.12 | E45: =SUM(B45:D45)
A46: Office Expenses & Rent Allocation | B46: 7.35 | C46: 2.36 | D46: 2.4 | E46: =SUM(B46:D46)
A47: Overhead Allocation & Chargebacks | B47: 7.12 | C47: 2.33 | D47: 2.43 | E47: =SUM(B47:D47)
A48: Other | B48: 4.35 | C48: 1.38 | D48: 2.63 | E48: =SUM(B48:D48)
A49: Total Partners | B49: =SUM(B42:B48) | C49: =SUM(C42:C48) | D49: =SUM(D42:D48) | E49: =SUM(E42:E48)
A51: Content
A52: Employee Expenses | B52: 10.34 | C52: 3.57 | D52: 3.81 | E52: =SUM(B52:D52)
A53: Professional Fees and Outsourcing Expenses | B53: 2.94 | C53: 0.92 | D53: 0.92 | E53: =SUM(B53:D53)
A54: Software and Maintenance Expense | B54: 1.88 | C54: 0.59 | D54: 0.69 | E54: =SUM(B54:D54)
A55: Office Expenses & Rent Allocation | B55: 1.61 | C55: 0.52 | D55: 0.54 | E55: =SUM(B55:D55)
A56: Overhead Allocation & Chargebacks | B56: 1.53 | C56: 0.49 | D56: 0.55 | E56: =SUM(B56:D56)
A57: Other | B57: 1.04 | C57: 0 | D57: 0.47 | E57: =SUM(B57:D57)
A58: Total Content | B58: =SUM(B52:B57) | C58: =SUM(C52:C57) | D58: =SUM(D52:D57) | E58: =SUM(E52:E57)
A60: R&D
A61: Employee Expenses | B61: 211.24 | C61: 60.47 | D61: 43.24 | E61: =SUM(B61:D61)
A62: Professional Fees and Outsourcing Expenses | B62: 37.52 | C62: 12.05 | D62: 8.26 | E62: =SUM(B62:D62)
A63: Software and Maintenance Expense | B63: 31.01 | C63: 10.18 | D63: 6.82 | E63: =SUM(B63:D63)
A64: Advertising and Promotion Expense | B64: 0 | C64: 0 | D64: 0 | E64: =SUM(B64:D64)
A65: Office Expenses & Rent Allocation | B65: 14.97 | C65: 4.59 | D65: 3.36 | E65: =SUM(B65:D65)
A66: Overhead Allocation & Chargebacks | B66: 16.03 | C66: 5.22 | D66: 3.65 | E66: =SUM(B66:D66)
A67: Other | B67: -0.63 | C67: -0.9 | D67: 3.43 | E67: =SUM(B67:D67)
A68: Total R&D | B68: =SUM(B61:B67) | C68: =SUM(C61:C67) | D68: =SUM(D61:D67) | E68: =SUM(E61:E67)
A70: Product Management
A71: Employee Expenses | B71: 96.24 | C71: 24.58 | D71: 19.47 | E71: =SUM(B71:D71)
A72: Professional Fees and Outsourcing Expenses | B72: 24.98 | C72: 7.49 | D72: 5.71 | E72: =SUM(B72:D72)
A73: Software and Maintenance Expense | B73: 17.11 | C73: 4.53 | D73: 3.46 | E73: =SUM(B73:D73)
A74: Office Expenses & Rent Allocation | B74: 14.51 | C74: 3.87 | D74: 2.95 | E74: =SUM(B74:D74)
A75: Overhead Allocation & Chargebacks | B75: 14.67 | C75: 3.59 | D75: 2.87 | E75: =SUM(B75:D75)
A76: Other | B76: 2.96 | C76: 3.19 | D76: -0.14 | E76: =SUM(B76:D76)
A77: Total Product Management | B77: =SUM(B71:B76) | C77: =SUM(C71:C76) | D77: =SUM(D71:D76) | E77: =SUM(E71:E76)

Sheet Charts & Visuals
B1: Keystone BenefitTech, Inc.
B2: Charts & Visuals Dashboard — FY2025 | O2: Last Updated: 2026-02-28
B5: PRODUCT SELECTOR — Choose a product to filter Section 1 charts
B6: Product: | C6: iGO | D6: Click the dropdown arrow to select iGO, Affirm, InsureSight, or DocFast
B8: SECTION 1 | SELECTED PRODUCT DASHBOARD
B10: Revenue vs Cost of Revenue — Monthly ($K) | J10: Contribution Margin % — Monthly Trend
B30: Expense Breakdown by Department — Full Year
B50: SECTION 2 | ALL-PRODUCTS COMPARISON
B52: Monthly Revenue by Product ($K) | J52: Contribution Margin % by Product
B72: Full Year Revenue Mix — FY2025
B92: SECTION 3 | ADVANCED ANALYTICS
B94: Revenue vs COGS vs Contribution Margin — By Product | J94: Department Cost Distribution Across Products
A199: LOOKUP TABLES — DO NOT EDIT (used by charts above)
A200: Metric | B200: Jan | C200: Feb | D200: Mar | E200: Apr | F200: May | G200: Jun | H200: Jul | I200: Aug | J200: Sep | K200: Oct | L200: Nov | M200: Dec
A201: Revenue | B201: =IF($C$6="iGO",'Product Line Summary'!B8,IF($C$6="Affirm",'Product Line Summary'!B16,IF($C$6="InsureSight",'Product Line Summary'!B24,'Product Line Summary'!B32))) | C201: =IF($C$6="iGO",'Product Line Summary'!C8,IF($C$6="Affirm",'Product Line Summary'!C16,IF($C$6="InsureSight",'Product Line Summary'!C24,'Product Line Summary'!C32))) | D201: =IF($C$6="iGO",'Product Line Summary'!D8,IF($C$6="Affirm",'Product Line Summary'!D16,IF($C$6="InsureSight",'Product Line Summary'!D24,'Product Line Summary'!D32))) | E201: =IF($C$6="iGO",'Product Line Summary'!E8,IF($C$6="Affirm",'Product Line Summary'!E16,IF($C$6="InsureSight",'Product Line Summary'!E24,'Product Line Summary'!E32))) | F201: =IF($C$6="iGO",'Product Line Summary'!F8,IF($C$6="Affirm",'Product Line Summary'!F16,IF($C$6="InsureSight",'Product Line Summary'!F24,'Product Line Summary'!F32))) | G201: =IF($C$6="iGO",'Product Line Summary'!G8,IF($C$6="Affirm",'Product Line Summary'!G16,IF($C$6="InsureSight",'Product Line Summary'!G24,'Product Line Summary'!G32))) | H201: =IF($C$6="iGO",'Product Line Summary'!H8,IF($C$6="Affirm",'Product Line Summary'!H16,IF($C$6="InsureSight",'Product Line Summary'!H24,'Product Line Summary'!H32))) | I201: =IF($C$6="iGO",'Product Line Summary'!I8,IF($C$6="Affirm",'Product Line Summary'!I16,IF($C$6="InsureSight",'Product Line Summary'!I24,'Product Line Summary'!I32))) | ... M201: =IF($C$6="iGO",'Product Line Summary'!M8,IF($C$6="Affirm",'Product Line Summary'!M16,IF($C$6="InsureSight",'Product Line Summary'!M24,'Product Line Summary'!M32)))
A202: Cost of Revenue | B202: =IF($C$6="iGO",'Product Line Summary'!B9,IF($C$6="Affirm",'Product Line Summary'!B17,IF($C$6="InsureSight",'Product Line Summary'!B25,'Product Line Summary'!B33))) | C202: =IF($C$6="iGO",'Product Line Summary'!C9,IF($C$6="Affirm",'Product Line Summary'!C17,IF($C$6="InsureSight",'Product Line Summary'!C25,'Product Line Summary'!C33))) | D202: =IF($C$6="iGO",'Product Line Summary'!D9,IF($C$6="Affirm",'Product Line Summary'!D17,IF($C$6="InsureSight",'Product Line Summary'!D25,'Product Line Summary'!D33))) | E202: =IF($C$6="iGO",'Product Line Summary'!E9,IF($C$6="Affirm",'Product Line Summary'!E17,IF($C$6="InsureSight",'Product Line Summary'!E25,'Product Line Summary'!E33))) | F202: =IF($C$6="iGO",'Product Line Summary'!F9,IF($C$6="Affirm",'Product Line Summary'!F17,IF($C$6="InsureSight",'Product Line Summary'!F25,'Product Line Summary'!F33))) | G202: =IF($C$6="iGO",'Product Line Summary'!G9,IF($C$6="Affirm",'Product Line Summary'!G17,IF($C$6="InsureSight",'Product Line Summary'!G25,'Product Line Summary'!G33))) | H202: =IF($C$6="iGO",'Product Line Summary'!H9,IF($C$6="Affirm",'Product Line Summary'!H17,IF($C$6="InsureSight",'Product Line Summary'!H25,'Product Line Summary'!H33))) | I202: =IF($C$6="iGO",'Product Line Summary'!I9,IF($C$6="Affirm",'Product Line Summary'!I17,IF($C$6="InsureSight",'Product Line Summary'!I25,'Product Line Summary'!I33))) | ... M202: =IF($C$6="iGO",'Product Line Summary'!M9,IF($C$6="Affirm",'Product Line Summary'!M17,IF($C$6="InsureSight",'Product Line Summary'!M25,'Product Line Summary'!M33)))
A203: Contribution Margin $ | B203: =IF($C$6="iGO",'Product Line Summary'!B10,IF($C$6="Affirm",'Product Line Summary'!B18,IF($C$6="InsureSight",'Product Line Summary'!B26,'Product Line Summary'!B34))) | C203: =IF($C$6="iGO",'Product Line Summary'!C10,IF($C$6="Affirm",'Product Line Summary'!C18,IF($C$6="InsureSight",'Product Line Summary'!C26,'Product Line Summary'!C34))) | D203: =IF($C$6="iGO",'Product Line Summary'!D10,IF($C$6="Affirm",'Product Line Summary'!D18,IF($C$6="InsureSight",'Product Line Summary'!D26,'Product Line Summary'!D34))) | E203: =IF($C$6="iGO",'Product Line Summary'!E10,IF($C$6="Affirm",'Product Line Summary'!E18,IF($C$6="InsureSight",'Product Line Summary'!E26,'Product Line Summary'!E34))) | F203: =IF($C$6="iGO",'Product Line Summary'!F10,IF($C$6="Affirm",'Product Line Summary'!F18,IF($C$6="InsureSight",'Product Line Summary'!F26,'Product Line Summary'!F34))) | G203: =IF($C$6="iGO",'Product Line Summary'!G10,IF($C$6="Affirm",'Product Line Summary'!G18,IF($C$6="InsureSight",'Product Line Summary'!G26,'Product Line Summary'!G34))) | H203: =IF($C$6="iGO",'Product Line Summary'!H10,IF($C$6="Affirm",'Product Line Summary'!H18,IF($C$6="InsureSight",'Product Line Summary'!H26,'Product Line Summary'!H34))) | I203: =IF($C$6="iGO",'Product Line Summary'!I10,IF($C$6="Affirm",'Product Line Summary'!I18,IF($C$6="InsureSight",'Product Line Summary'!I26,'Product Line Summary'!I34))) | ... M203: =IF($C$6="iGO",'Product Line Summary'!M10,IF($C$6="Affirm",'Product Line Summary'!M18,IF($C$6="InsureSight",'Product Line Summary'!M26,'Product Line Summary'!M34)))
A204: Contribution Margin % | B204: =IF($C$6="iGO",'Product Line Summary'!B11,IF($C$6="Affirm",'Product Line Summary'!B19,IF($C$6="InsureSight",'Product Line Summary'!B27,'Product Line Summary'!B35))) | C204: =IF($C$6="iGO",'Product Line Summary'!C11,IF($C$6="Affirm",'Product Line Summary'!C19,IF($C$6="InsureSight",'Product Line Summary'!C27,'Product Line Summary'!C35))) | D204: =IF($C$6="iGO",'Product Line Summary'!D11,IF($C$6="Affirm",'Product Line Summary'!D19,IF($C$6="InsureSight",'Product Line Summary'!D27,'Product Line Summary'!D35))) | E204: =IF($C$6="iGO",'Product Line Summary'!E11,IF($C$6="Affirm",'Product Line Summary'!E19,IF($C$6="InsureSight",'Product Line Summary'!E27,'Product Line Summary'!E35))) | F204: =IF($C$6="iGO",'Product Line Summary'!F11,IF($C$6="Affirm",'Product Line Summary'!F19,IF($C$6="InsureSight",'Product Line Summary'!F27,'Product Line Summary'!F35))) | G204: =IF($C$6="iGO",'Product Line Summary'!G11,IF($C$6="Affirm",'Product Line Summary'!G19,IF($C$6="InsureSight",'Product Line Summary'!G27,'Product Line Summary'!G35))) | H204: =IF($C$6="iGO",'Product Line Summary'!H11,IF($C$6="Affirm",'Product Line Summary'!H19,IF($C$6="InsureSight",'Product Line Summary'!H27,'Product Line Summary'!H35))) | I204: =IF($C$6="iGO",'Product Line Summary'!I11,IF($C$6="Affirm",'Product Line Summary'!I19,IF($C$6="InsureSight",'Product Line Summary'!I27,'Product Line Summary'!I35))) | ... M204: =IF($C$6="iGO",'Product Line Summary'!M11,IF($C$6="Affirm",'Product Line Summary'!M19,IF($C$6="InsureSight",'Product Line Summary'!M27,'Product Line Summary'!M35)))
A205: CM + R&D $ | B205: =IF($C$6="iGO",'Product Line Summary'!B12,IF($C$6="Affirm",'Product Line Summary'!B20,IF($C$6="InsureSight",'Product Line Summary'!B28,'Product Line Summary'!B36))) | C205: =IF($C$6="iGO",'Product Line Summary'!C12,IF($C$6="Affirm",'Product Line Summary'!C20,IF($C$6="InsureSight",'Product Line Summary'!C28,'Product Line Summary'!C36))) | D205: =IF($C$6="iGO",'Product Line Summary'!D12,IF($C$6="Affirm",'Product Line Summary'!D20,IF($C$6="InsureSight",'Product Line Summary'!D28,'Product Line Summary'!D36))) | E205: =IF($C$6="iGO",'Product Line Summary'!E12,IF($C$6="Affirm",'Product Line Summary'!E20,IF($C$6="InsureSight",'Product Line Summary'!E28,'Product Line Summary'!E36))) | F205: =IF($C$6="iGO",'Product Line Summary'!F12,IF($C$6="Affirm",'Product Line Summary'!F20,IF($C$6="InsureSight",'Product Line Summary'!F28,'Product Line Summary'!F36))) | G205: =IF($C$6="iGO",'Product Line Summary'!G12,IF($C$6="Affirm",'Product Line Summary'!G20,IF($C$6="InsureSight",'Product Line Summary'!G28,'Product Line Summary'!G36))) | H205: =IF($C$6="iGO",'Product Line Summary'!H12,IF($C$6="Affirm",'Product Line Summary'!H20,IF($C$6="InsureSight",'Product Line Summary'!H28,'Product Line Summary'!H36))) | I205: =IF($C$6="iGO",'Product Line Summary'!I12,IF($C$6="Affirm",'Product Line Summary'!I20,IF($C$6="InsureSight",'Product Line Summary'!I28,'Product Line Summary'!I36))) | ... M205: =IF($C$6="iGO",'Product Line Summary'!M12,IF($C$6="Affirm",'Product Line Summary'!M20,IF($C$6="InsureSight",'Product Line Summary'!M28,'Product Line Summary'!M36)))
A206: CM + R&D % | B206: =IF($C$6="iGO",'Product Line Summary'!B13,IF($C$6="Affirm",'Product Line Summary'!B21,IF($C$6="InsureSight",'Product Line Summary'!B29,'Product Line Summary'!B37))) | C206: =IF($C$6="iGO",'Product Line Summary'!C13,IF($C$6="Affirm",'Product Line Summary'!C21,IF($C$6="InsureSight",'Product Line Summary'!C29,'Product Line Summary'!C37))) | D206: =IF($C$6="iGO",'Product Line Summary'!D13,IF($C$6="Affirm",'Product Line Summary'!D21,IF($C$6="InsureSight",'Product Line Summary'!D29,'Product Line Summary'!D37))) | E206: =IF($C$6="iGO",'Product Line Summary'!E13,IF($C$6="Affirm",'Product Line Summary'!E21,IF($C$6="InsureSight",'Product Line Summary'!E29,'Product Line Summary'!E37))) | F206: =IF($C$6="iGO",'Product Line Summary'!F13,IF($C$6="Affirm",'Product Line Summary'!F21,IF($C$6="InsureSight",'Product Line Summary'!F29,'Product Line Summary'!F37))) | G206: =IF($C$6="iGO",'Product Line Summary'!G13,IF($C$6="Affirm",'Product Line Summary'!G21,IF($C$6="InsureSight",'Product Line Summary'!G29,'Product Line Summary'!G37))) | H206: =IF($C$6="iGO",'Product Line Summary'!H13,IF($C$6="Affirm",'Product Line Summary'!H21,IF($C$6="InsureSight",'Product Line Summary'!H29,'Product Line Summary'!H37))) | I206: =IF($C$6="iGO",'Product Line Summary'!I13,IF($C$6="Affirm",'Product Line Summary'!I21,IF($C$6="InsureSight",'Product Line Summary'!I29,'Product Line Summary'!I37))) | ... M206: =IF($C$6="iGO",'Product Line Summary'!M13,IF($C$6="Affirm",'Product Line Summary'!M21,IF($C$6="InsureSight",'Product Line Summary'!M29,'Product Line Summary'!M37)))
A208: Department | B208: Jan | C208: Feb | D208: Mar | E208: Apr | F208: May | G208: Jun | H208: Jul | I208: Aug | J208: Sep | K208: Oct | L208: Nov | M208: Dec
A209: NetOps | B209: =IF($C$6="iGO",'Product Line Summary'!B43,IF($C$6="Affirm",'Product Line Summary'!B53,IF($C$6="InsureSight",'Product Line Summary'!B63,'Product Line Summary'!B73))) | C209: =IF($C$6="iGO",'Product Line Summary'!C43,IF($C$6="Affirm",'Product Line Summary'!C53,IF($C$6="InsureSight",'Product Line Summary'!C63,'Product Line Summary'!C73))) | D209: =IF($C$6="iGO",'Product Line Summary'!D43,IF($C$6="Affirm",'Product Line Summary'!D53,IF($C$6="InsureSight",'Product Line Summary'!D63,'Product Line Summary'!D73))) | E209: =IF($C$6="iGO",'Product Line Summary'!E43,IF($C$6="Affirm",'Product Line Summary'!E53,IF($C$6="InsureSight",'Product Line Summary'!E63,'Product Line Summary'!E73))) | F209: =IF($C$6="iGO",'Product Line Summary'!F43,IF($C$6="Affirm",'Product Line Summary'!F53,IF($C$6="InsureSight",'Product Line Summary'!F63,'Product Line Summary'!F73))) | G209: =IF($C$6="iGO",'Product Line Summary'!G43,IF($C$6="Affirm",'Product Line Summary'!G53,IF($C$6="InsureSight",'Product Line Summary'!G63,'Product Line Summary'!G73))) | H209: =IF($C$6="iGO",'Product Line Summary'!H43,IF($C$6="Affirm",'Product Line Summary'!H53,IF($C$6="InsureSight",'Product Line Summary'!H63,'Product Line Summary'!H73))) | I209: =IF($C$6="iGO",'Product Line Summary'!I43,IF($C$6="Affirm",'Product Line Summary'!I53,IF($C$6="InsureSight",'Product Line Summary'!I63,'Product Line Summary'!I73))) | ... M209: =IF($C$6="iGO",'Product Line Summary'!M43,IF($C$6="Affirm",'Product Line Summary'!M53,IF($C$6="InsureSight",'Product Line Summary'!M63,'Product Line Summary'!M73))) | N209: =SUM(B209:M209)
A210: Security | B210: =IF($C$6="iGO",'Product Line Summary'!B44,IF($C$6="Affirm",'Product Line Summary'!B54,IF($C$6="InsureSight",'Product Line Summary'!B64,'Product Line Summary'!B74))) | C210: =IF($C$6="iGO",'Product Line Summary'!C44,IF($C$6="Affirm",'Product Line Summary'!C54,IF($C$6="InsureSight",'Product Line Summary'!C64,'Product Line Summary'!C74))) | D210: =IF($C$6="iGO",'Product Line Summary'!D44,IF($C$6="Affirm",'Product Line Summary'!D54,IF($C$6="InsureSight",'Product Line Summary'!D64,'Product Line Summary'!D74))) | E210: =IF($C$6="iGO",'Product Line Summary'!E44,IF($C$6="Affirm",'Product Line Summary'!E54,IF($C$6="InsureSight",'Product Line Summary'!E64,'Product Line Summary'!E74))) | F210: =IF($C$6="iGO",'Product Line Summary'!F44,IF($C$6="Affirm",'Product Line Summary'!F54,IF($C$6="InsureSight",'Product Line Summary'!F64,'Product Line Summary'!F74))) | G210: =IF($C$6="iGO",'Product Line Summary'!G44,IF($C$6="Affirm",'Product Line Summary'!G54,IF($C$6="InsureSight",'Product Line Summary'!G64,'Product Line Summary'!G74))) | H210: =IF($C$6="iGO",'Product Line Summary'!H44,IF($C$6="Affirm",'Product Line Summary'!H54,IF($C$6="InsureSight",'Product Line Summary'!H64,'Product Line Summary'!H74))) | I210: =IF($C$6="iGO",'Product Line Summary'!I44,IF($C$6="Affirm",'Product Line Summary'!I54,IF($C$6="InsureSight",'Product Line Summary'!I64,'Product Line Summary'!I74))) | ... M210: =IF($C$6="iGO",'Product Line Summary'!M44,IF($C$6="Affirm",'Product Line Summary'!M54,IF($C$6="InsureSight",'Product Line Summary'!M64,'Product Line Summary'!M74))) | N210: =SUM(B210:M210)
A211: Support | B211: =IF($C$6="iGO",'Product Line Summary'!B45,IF($C$6="Affirm",'Product Line Summary'!B55,IF($C$6="InsureSight",'Product Line Summary'!B65,'Product Line Summary'!B75))) | C211: =IF($C$6="iGO",'Product Line Summary'!C45,IF($C$6="Affirm",'Product Line Summary'!C55,IF($C$6="InsureSight",'Product Line Summary'!C65,'Product Line Summary'!C75))) | D211: =IF($C$6="iGO",'Product Line Summary'!D45,IF($C$6="Affirm",'Product Line Summary'!D55,IF($C$6="InsureSight",'Product Line Summary'!D65,'Product Line Summary'!D75))) | E211: =IF($C$6="iGO",'Product Line Summary'!E45,IF($C$6="Affirm",'Product Line Summary'!E55,IF($C$6="InsureSight",'Product Line Summary'!E65,'Product Line Summary'!E75))) | F211: =IF($C$6="iGO",'Product Line Summary'!F45,IF($C$6="Affirm",'Product Line Summary'!F55,IF($C$6="InsureSight",'Product Line Summary'!F65,'Product Line Summary'!F75))) | G211: =IF($C$6="iGO",'Product Line Summary'!G45,IF($C$6="Affirm",'Product Line Summary'!G55,IF($C$6="InsureSight",'Product Line Summary'!G65,'Product Line Summary'!G75))) | H211: =IF($C$6="iGO",'Product Line Summary'!H45,IF($C$6="Affirm",'Product Line Summary'!H55,IF($C$6="InsureSight",'Product Line Summary'!H65,'Product Line Summary'!H75))) | I211: =IF($C$6="iGO",'Product Line Summary'!I45,IF($C$6="Affirm",'Product Line Summary'!I55,IF($C$6="InsureSight",'Product Line Summary'!I65,'Product Line Summary'!I75))) | ... M211: =IF($C$6="iGO",'Product Line Summary'!M45,IF($C$6="Affirm",'Product Line Summary'!M55,IF($C$6="InsureSight",'Product Line Summary'!M65,'Product Line Summary'!M75))) | N211: =SUM(B211:M211)
A212: Partners | B212: =IF($C$6="iGO",'Product Line Summary'!B46,IF($C$6="Affirm",'Product Line Summary'!B56,IF($C$6="InsureSight",'Product Line Summary'!B66,'Product Line Summary'!B76))) | C212: =IF($C$6="iGO",'Product Line Summary'!C46,IF($C$6="Affirm",'Product Line Summary'!C56,IF($C$6="InsureSight",'Product Line Summary'!C66,'Product Line Summary'!C76))) | D212: =IF($C$6="iGO",'Product Line Summary'!D46,IF($C$6="Affirm",'Product Line Summary'!D56,IF($C$6="InsureSight",'Product Line Summary'!D66,'Product Line Summary'!D76))) | E212: =IF($C$6="iGO",'Product Line Summary'!E46,IF($C$6="Affirm",'Product Line Summary'!E56,IF($C$6="InsureSight",'Product Line Summary'!E66,'Product Line Summary'!E76))) | F212: =IF($C$6="iGO",'Product Line Summary'!F46,IF($C$6="Affirm",'Product Line Summary'!F56,IF($C$6="InsureSight",'Product Line Summary'!F66,'Product Line Summary'!F76))) | G212: =IF($C$6="iGO",'Product Line Summary'!G46,IF($C$6="Affirm",'Product Line Summary'!G56,IF($C$6="InsureSight",'Product Line Summary'!G66,'Product Line Summary'!G76))) | H212: =IF($C$6="iGO",'Product Line Summary'!H46,IF($C$6="Affirm",'Product Line Summary'!H56,IF($C$6="InsureSight",'Product Line Summary'!H66,'Product Line Summary'!H76))) | I212: =IF($C$6="iGO",'Product Line Summary'!I46,IF($C$6="Affirm",'Product Line Summary'!I56,IF($C$6="InsureSight",'Product Line Summary'!I66,'Product Line Summary'!I76))) | ... M212: =IF($C$6="iGO",'Product Line Summary'!M46,IF($C$6="Affirm",'Product Line Summary'!M56,IF($C$6="InsureSight",'Product Line Summary'!M66,'Product Line Summary'!M76))) | N212: =SUM(B212:M212)
A213: Content | B213: =IF($C$6="iGO",'Product Line Summary'!B47,IF($C$6="Affirm",'Product Line Summary'!B57,IF($C$6="InsureSight",'Product Line Summary'!B67,'Product Line Summary'!B77))) | C213: =IF($C$6="iGO",'Product Line Summary'!C47,IF($C$6="Affirm",'Product Line Summary'!C57,IF($C$6="InsureSight",'Product Line Summary'!C67,'Product Line Summary'!C77))) | D213: =IF($C$6="iGO",'Product Line Summary'!D47,IF($C$6="Affirm",'Product Line Summary'!D57,IF($C$6="InsureSight",'Product Line Summary'!D67,'Product Line Summary'!D77))) | E213: =IF($C$6="iGO",'Product Line Summary'!E47,IF($C$6="Affirm",'Product Line Summary'!E57,IF($C$6="InsureSight",'Product Line Summary'!E67,'Product Line Summary'!E77))) | F213: =IF($C$6="iGO",'Product Line Summary'!F47,IF($C$6="Affirm",'Product Line Summary'!F57,IF($C$6="InsureSight",'Product Line Summary'!F67,'Product Line Summary'!F77))) | G213: =IF($C$6="iGO",'Product Line Summary'!G47,IF($C$6="Affirm",'Product Line Summary'!G57,IF($C$6="InsureSight",'Product Line Summary'!G67,'Product Line Summary'!G77))) | H213: =IF($C$6="iGO",'Product Line Summary'!H47,IF($C$6="Affirm",'Product Line Summary'!H57,IF($C$6="InsureSight",'Product Line Summary'!H67,'Product Line Summary'!H77))) | I213: =IF($C$6="iGO",'Product Line Summary'!I47,IF($C$6="Affirm",'Product Line Summary'!I57,IF($C$6="InsureSight",'Product Line Summary'!I67,'Product Line Summary'!I77))) | ... M213: =IF($C$6="iGO",'Product Line Summary'!M47,IF($C$6="Affirm",'Product Line Summary'!M57,IF($C$6="InsureSight",'Product Line Summary'!M67,'Product Line Summary'!M77))) | N213: =SUM(B213:M213)
A214: Research & Development | B214: =IF($C$6="iGO",'Product Line Summary'!B48,IF($C$6="Affirm",'Product Line Summary'!B58,IF($C$6="InsureSight",'Product Line Summary'!B68,'Product Line Summary'!B78))) | C214: =IF($C$6="iGO",'Product Line Summary'!C48,IF($C$6="Affirm",'Product Line Summary'!C58,IF($C$6="InsureSight",'Product Line Summary'!C68,'Product Line Summary'!C78))) | D214: =IF($C$6="iGO",'Product Line Summary'!D48,IF($C$6="Affirm",'Product Line Summary'!D58,IF($C$6="InsureSight",'Product Line Summary'!D68,'Product Line Summary'!D78))) | E214: =IF($C$6="iGO",'Product Line Summary'!E48,IF($C$6="Affirm",'Product Line Summary'!E58,IF($C$6="InsureSight",'Product Line Summary'!E68,'Product Line Summary'!E78))) | F214: =IF($C$6="iGO",'Product Line Summary'!F48,IF($C$6="Affirm",'Product Line Summary'!F58,IF($C$6="InsureSight",'Product Line Summary'!F68,'Product Line Summary'!F78))) | G214: =IF($C$6="iGO",'Product Line Summary'!G48,IF($C$6="Affirm",'Product Line Summary'!G58,IF($C$6="InsureSight",'Product Line Summary'!G68,'Product Line Summary'!G78))) | H214: =IF($C$6="iGO",'Product Line Summary'!H48,IF($C$6="Affirm",'Product Line Summary'!H58,IF($C$6="InsureSight",'Product Line Summary'!H68,'Product Line Summary'!H78))) | I214: =IF($C$6="iGO",'Product Line Summary'!I48,IF($C$6="Affirm",'Product Line Summary'!I58,IF($C$6="InsureSight",'Product Line Summary'!I68,'Product Line Summary'!I78))) | ... M214: =IF($C$6="iGO",'Product Line Summary'!M48,IF($C$6="Affirm",'Product Line Summary'!M58,IF($C$6="InsureSight",'Product Line Summary'!M68,'Product Line Summary'!M78))) | N214: =SUM(B214:M214)
A215: Product Management | B215: =IF($C$6="iGO",'Product Line Summary'!B49,IF($C$6="Affirm",'Product Line Summary'!B59,IF($C$6="InsureSight",'Product Line Summary'!B69,'Product Line Summary'!B79))) | C215: =IF($C$6="iGO",'Product Line Summary'!C49,IF($C$6="Affirm",'Product Line Summary'!C59,IF($C$6="InsureSight",'Product Line Summary'!C69,'Product Line Summary'!C79))) | D215: =IF($C$6="iGO",'Product Line Summary'!D49,IF($C$6="Affirm",'Product Line Summary'!D59,IF($C$6="InsureSight",'Product Line Summary'!D69,'Product Line Summary'!D79))) | E215: =IF($C$6="iGO",'Product Line Summary'!E49,IF($C$6="Affirm",'Product Line Summary'!E59,IF($C$6="InsureSight",'Product Line Summary'!E69,'Product Line Summary'!E79))) | F215: =IF($C$6="iGO",'Product Line Summary'!F49,IF($C$6="Affirm",'Product Line Summary'!F59,IF($C$6="InsureSight",'Product Line Summary'!F69,'Product Line Summary'!F79))) | G215: =IF($C$6="iGO",'Product Line Summary'!G49,IF($C$6="Affirm",'Product Line Summary'!G59,IF($C$6="InsureSight",'Product Line Summary'!G69,'Product Line Summary'!G79))) | H215: =IF($C$6="iGO",'Product Line Summary'!H49,IF($C$6="Affirm",'Product Line Summary'!H59,IF($C$6="InsureSight",'Product Line Summary'!H69,'Product Line Summary'!H79))) | I215: =IF($C$6="iGO",'Product Line Summary'!I49,IF($C$6="Affirm",'Product Line Summary'!I59,IF($C$6="InsureSight",'Product Line Summary'!I69,'Product Line Summary'!I79))) | ... M215: =IF($C$6="iGO",'Product Line Summary'!M49,IF($C$6="Affirm",'Product Line Summary'!M59,IF($C$6="InsureSight",'Product Line Summary'!M69,'Product Line Summary'!M79))) | N215: =SUM(B215:M215)
A218: Product | B218: FY Revenue | C218: FY COGS | D218: FY CM$
A219: iGO | B219: ='Product Line Summary'!R8 | C219: ='Product Line Summary'!R9 | D219: ='Product Line Summary'!R10
A220: Affirm | B220: ='Product Line Summary'!R16 | C220: ='Product Line Summary'!R17 | D220: ='Product Line Summary'!R18
A221: InsureSight | B221: ='Product Line Summary'!R24 | C221: ='Product Line Summary'!R25 | D221: ='Product Line Summary'!R26
A222: DocFast | B222: ='Product Line Summary'!R32 | C222: ='Product Line Summary'!R33 | D222: ='Product Line Summary'!R34
A224: Department | B224: iGO | C224: Affirm | D224: InsureSight | E224: DocFast
A225: NetOps | B225: ='Product Line Summary'!R43 | C225: ='Product Line Summary'!R53 | D225: ='Product Line Summary'!R63 | E225: ='Product Line Summary'!R73
A226: Security | B226: ='Product Line Summary'!R44 | C226: ='Product Line Summary'!R54 | D226: ='Product Line Summary'!R64 | E226: ='Product Line Summary'!R74
A227: Support | B227: ='Product Line Summary'!R45 | C227: ='Product Line Summary'!R55 | D227: ='Product Line Summary'!R65 | E227: ='Product Line Summary'!R75
A228: Partners | B228: ='Product Line Summary'!R46 | C228: ='Product Line Summary'!R56 | D228: ='Product Line Summary'!R66 | E228: ='Product Line Summary'!R76
A229: Content | B229: ='Product Line Summary'!R47 | C229: ='Product Line Summary'!R57 | D229: ='Product Line Summary'!R67 | E229: ='Product Line Summary'!R77
A230: R&D | B230: ='Product Line Summary'!R48 | C230: ='Product Line Summary'!R58 | D230: ='Product Line Summary'!R68 | E230: ='Product Line Summary'!R78
A231: Product Mgmt | B231: ='Product Line Summary'!R49 | C231: ='Product Line Summary'!R59 | D231: ='Product Line Summary'!R69 | E231: ='Product Line Summary'!R79
A233: Month | B233: iGO | C233: Affirm | D233: InsureSight | E233: DocFast
A234: Jan | B234: ='Product Line Summary'!B8 | C234: ='Product Line Summary'!B16 | D234: ='Product Line Summary'!B24 | E234: ='Product Line Summary'!B32
A235: Feb | B235: ='Product Line Summary'!C8 | C235: ='Product Line Summary'!C16 | D235: ='Product Line Summary'!C24 | E235: ='Product Line Summary'!C32
A236: Mar | B236: ='Product Line Summary'!D8 | C236: ='Product Line Summary'!D16 | D236: ='Product Line Summary'!D24 | E236: ='Product Line Summary'!D32
A237: Apr | B237: ='Product Line Summary'!E8 | C237: ='Product Line Summary'!E16 | D237: ='Product Line Summary'!E24 | E237: ='Product Line Summary'!E32
A238: May | B238: ='Product Line Summary'!F8 | C238: ='Product Line Summary'!F16 | D238: ='Product Line Summary'!F24 | E238: ='Product Line Summary'!F32
A239: Jun | B239: ='Product Line Summary'!G8 | C239: ='Product Line Summary'!G16 | D239: ='Product Line Summary'!G24 | E239: ='Product Line Summary'!G32
A240: Jul | B240: ='Product Line Summary'!H8 | C240: ='Product Line Summary'!H16 | D240: ='Product Line Summary'!H24 | E240: ='Product Line Summary'!H32
A241: Aug | B241: ='Product Line Summary'!I8 | C241: ='Product Line Summary'!I16 | D241: ='Product Line Summary'!I24 | E241: ='Product Line Summary'!I32
A242: Sep | B242: ='Product Line Summary'!J8 | C242: ='Product Line Summary'!J16 | D242: ='Product Line Summary'!J24 | E242: ='Product Line Summary'!J32
A243: Oct | B243: ='Product Line Summary'!K8 | C243: ='Product Line Summary'!K16 | D243: ='Product Line Summary'!K24 | E243: ='Product Line Summary'!K32
A244: Nov | B244: ='Product Line Summary'!L8 | C244: ='Product Line Summary'!L16 | D244: ='Product Line Summary'!L24 | E244: ='Product Line Summary'!L32
A245: Dec | B245: ='Product Line Summary'!M8 | C245: ='Product Line Summary'!M16 | D245: ='Product Line Summary'!M24 | E245: ='Product Line Summary'!M32
A247: Month | B247: iGO | C247: Affirm | D247: InsureSight | E247: DocFast
A248: Jan | B248: ='Product Line Summary'!B11 | C248: ='Product Line Summary'!B19 | D248: ='Product Line Summary'!B27 | E248: ='Product Line Summary'!B35
A249: Feb | B249: ='Product Line Summary'!C11 | C249: ='Product Line Summary'!C19 | D249: ='Product Line Summary'!C27 | E249: ='Product Line Summary'!C35
A250: Mar | B250: ='Product Line Summary'!D11 | C250: ='Product Line Summary'!D19 | D250: ='Product Line Summary'!D27 | E250: ='Product Line Summary'!D35
A251: Apr | B251: ='Product Line Summary'!E11 | C251: ='Product Line Summary'!E19 | D251: ='Product Line Summary'!E27 | E251: ='Product Line Summary'!E35
A252: May | B252: ='Product Line Summary'!F11 | C252: ='Product Line Summary'!F19 | D252: ='Product Line Summary'!F27 | E252: ='Product Line Summary'!F35
A253: Jun | B253: ='Product Line Summary'!G11 | C253: ='Product Line Summary'!G19 | D253: ='Product Line Summary'!G27 | E253: ='Product Line Summary'!G35
A254: Jul | B254: ='Product Line Summary'!H11 | C254: ='Product Line Summary'!H19 | D254: ='Product Line Summary'!H27 | E254: ='Product Line Summary'!H35
A255: Aug | B255: ='Product Line Summary'!I11 | C255: ='Product Line Summary'!I19 | D255: ='Product Line Summary'!I27 | E255: ='Product Line Summary'!I35
A256: Sep | B256: ='Product Line Summary'!J11 | C256: ='Product Line Summary'!J19 | D256: ='Product Line Summary'!J27 | E256: ='Product Line Summary'!J35
A257: Oct | B257: ='Product Line Summary'!K11 | C257: ='Product Line Summary'!K19 | D257: ='Product Line Summary'!K27 | E257: ='Product Line Summary'!K35
A258: Nov | B258: ='Product Line Summary'!L11 | C258: ='Product Line Summary'!L19 | D258: ='Product Line Summary'!L27 | E258: ='Product Line Summary'!L35
A259: Dec | B259: ='Product Line Summary'!M11 | C259: ='Product Line Summary'!M19 | D259: ='Product Line Summary'!M27 | E259: ='Product Line Summary'!M35
A261: Product | B261: Revenue | C261: Cost of Revenue | D261: Contribution Margin
A262: iGO | B262: ='Product Line Summary'!R8 | C262: ='Product Line Summary'!R9 | D262: ='Product Line Summary'!R10
A263: Affirm | B263: ='Product Line Summary'!R16 | C263: ='Product Line Summary'!R17 | D263: ='Product Line Summary'!R18
A264: InsureSight | B264: ='Product Line Summary'!R24 | C264: ='Product Line Summary'!R25 | D264: ='Product Line Summary'!R26
A265: DocFast | B265: ='Product Line Summary'!R32 | C265: ='Product Line Summary'!R33 | D265: ='Product Line Summary'!R34

Sheet Checks
A1: Keystone BenefitTech, Inc. | E1: Last Updated: 2026-02-28
A2: Reconciliation Checks
A4: Check Name | B4: Sheet A Value | C4: Sheet B Value | D4: Difference | E4: Status
A5: Natural P&L NetOps iGO vs Func Summary Jan | B5: ='US January 2025 Natural P&L'!B21 | C5: ='Functional P&L Summary - Jan 25'!B12 | D5: =B5-C5 | E5: =IF(ABS(D5)<0.01,"PASS","FAIL")
A6: Natural P&L Security iGO vs Func Summary Jan | B6: ='US January 2025 Natural P&L'!B30 | C6: ='Functional P&L Summary - Jan 25'!B13 | D6: =B6-C6 | E6: =IF(ABS(D6)<0.01,"PASS","FAIL")
A7: Natural P&L Support iGO vs Func Summary Jan | B7: ='US January 2025 Natural P&L'!B39 | C7: ='Functional P&L Summary - Jan 25'!B14 | D7: =B7-C7 | E7: =IF(ABS(D7)<0.01,"PASS","FAIL")
A8: Natural P&L Partners iGO vs Func Summary Jan | B8: ='US January 2025 Natural P&L'!B49 | C8: ='Functional P&L Summary - Jan 25'!B15 | D8: =B8-C8 | E8: =IF(ABS(D8)<0.01,"PASS","FAIL")
A9: Natural P&L Content iGO vs Func Summary Jan | B9: ='US January 2025 Natural P&L'!B58 | C9: ='Functional P&L Summary - Jan 25'!B16 | D9: =B9-C9 | E9: =IF(ABS(D9)<0.01,"PASS","FAIL")
A10: Func Summary Jan: US Revenue vs SUM(products) | B10: ='Functional P&L Summary - Jan 25'!E9 | C10: ='Functional P&L Summary - Jan 25'!B9+'Functional P&L Summary - Jan 25'!C9+'Functional P&L Summary - Jan 25'!D9 | D10: =B10-C10 | E10: =IF(ABS(D10)<0.01,"PASS","FAIL")
A11: P&L Trend: Consolidated Rev Jan vs SUM(products) | B11: ='P&L - Monthly Trend'!B7 | C11: ='P&L - Monthly Trend'!B15+'P&L - Monthly Trend'!B23+'P&L - Monthly Trend'!B31+'P&L - Monthly Trend'!B39 | D11: =B11-C11 | E11: =IF(ABS(D11)<0.01,"PASS","FAIL")
A12: AWS Allocation Jan total vs Natural P&L NetOps AWS | B12: ='AWS Allocation'!F31 | C12: ='US January 2025 Natural P&L'!E15 | D12: =B12-C12 | E12: =IF(ABS(D12)<0.01,"PASS","FAIL")
A13: Revenue Share %s sum to 100% | B13: =Assumptions!B8+Assumptions!B9+Assumptions!B10+Assumptions!B11 | C13: 1 | D13: =B13-C13 | E13: =IF(ABS(D13)<0.01,"PASS","FAIL")
